{
  "ID": "f3426369-f9cb-4085-853f-38a43506380a",
  "Version": "2.3.4",
  "Name": "friendCard_Match_joinMatch",
  "Content": {
    "Content": {
      "Animation": {
        "Duration": 0,
        "Speed": 1.0,
        "Timelines": [],
        "ctype": "TimelineActionData"
      },
      "AnimationList": [],
      "ObjectData": {
        "Tag": 28,
        "Children": [
          {
            "ClipAble": false,
            "BackColorAlpha": 206,
            "ComboBoxIndex": 1,
            "SingleColor": {
              "R": 0,
              "G": 0,
              "B": 0
            },
            "FirstColor": {
              "R": 150,
              "G": 200
            },
            "EndColor": {},
            "ColorVector": {
              "ScaleY": 1.0
            },
            "Scale9OriginX": -22,
            "Scale9OriginY": -19,
            "Scale9Width": 44,
            "Scale9Height": 38,
            "TouchEnable": true,
            "AnchorPoint": {
              "ScaleX": 0.5,
              "ScaleY": 0.5
            },
            "Position": {
              "X": 0.0,
              "Y": 0.0
            },
            "Scale": {
              "ScaleX": 1.0,
              "ScaleY": 1.0
            },
            "CColor": {},
            "IconVisible": false,
            "PrePosition": {
              "X": 0.0,
              "Y": 0.0
            },
            "PreSize": {
              "X": 0.0,
              "Y": 0.0
            },
            "LeftMargin": -640.0,
            "RightMargin": -640.0,
            "TopMargin": -360.0,
            "BottomMargin": -360.0,
            "Tag": 29,
            "ActionTag": -297161110,
            "Size": {
              "X": 1280.0,
              "Y": 720.0
            },
            "Name": "block",
            "ctype": "PanelObjectData"
          },
          {
            "ClipAble": false,
            "BackColorAlpha": 102,
            "SingleColor": {
              "R": 150,
              "G": 200
            },
            "FirstColor": {
              "R": 150,
              "G": 200
            },
            "EndColor": {},
            "ColorVector": {
              "ScaleY": 1.0
            },
            "Scale9Width": 1,
            "Scale9Height": 1,
            "TouchEnable": true,
            "AnchorPoint": {
              "ScaleX": 0.5,
              "ScaleY": 0.5
            },
            "Position": {
              "X": 0.0,
              "Y": 0.0
            },
            "Scale": {
              "ScaleX": 1.0,
              "ScaleY": 1.0
            },
            "CColor": {},
            "IconVisible": false,
            "PrePosition": {
              "X": 0.0,
              "Y": 0.0
            },
            "PreSize": {
              "X": 0.0,
              "Y": 0.0
            },
            "LeftMargin": -640.0,
            "RightMargin": -640.0,
            "TopMargin": -360.0,
            "BottomMargin": -360.0,
            "Tag": 2934,
            "Children": [
              {
                "FileData": {
                  "Type": "Normal",
                  "Path": "friendCards/common/img_xiaotanchuang.png",
                  "Plist": ""
                },
                "Scale9Enable": true,
                "Scale9OriginX": 30,
                "Scale9OriginY": 30,
                "Scale9Width": 874,
                "Scale9Height": 442,
                "AnchorPoint": {
                  "ScaleX": 0.5,
                  "ScaleY": 0.5
                },
                "Position": {
                  "X": 640.0,
                  "Y": 360.0
                },
                "Scale": {
                  "ScaleX": 1.0,
                  "ScaleY": 1.0
                },
                "CColor": {},
                "IconVisible": false,
                "PositionPercentXEnabled": true,
                "PositionPercentYEnabled": true,
                "PrePosition": {
                  "X": 0.5,
                  "Y": 0.5
                },
                "PreSize": {
                  "X": 0.7297,
                  "Y": 0.6972
                },
                "LeftMargin": 173.0,
                "RightMargin": 173.0,
                "TopMargin": 109.0,
                "BottomMargin": 109.0,
                "Tag": 2935,
                "Children": [
                  {
                    "FileData": {
                      "Type": "Normal",
                      "Path": "friendCards/common/titel_2.png",
                      "Plist": ""
                    },
                    "Scale9OriginX": 148,
                    "Scale9OriginY": 21,
                    "Scale9Width": 153,
                    "Scale9Height": 22,
                    "AnchorPoint": {
                      "ScaleX": 0.5,
                      "ScaleY": 0.5
                    },
                    "Position": {
                      "X": 467.0,
                      "Y": 457.3065
                    },
                    "Scale": {
                      "ScaleX": 1.0,
                      "ScaleY": 1.0
                    },
                    "CColor": {},
                    "IconVisible": false,
                    "PositionPercentXEnabled": true,
                    "PrePosition": {
                      "X": 0.5,
                      "Y": 0.911
                    },
                    "PreSize": {
                      "X": 0.4807,
                      "Y": 0.1275
                    },
                    "LeftMargin": 242.5,
                    "RightMargin": 242.5,
                    "TopMargin": 12.6935,
                    "BottomMargin": 425.3065,
                    "Tag": 1704,
                    "ActionTag": 726804070,
                    "Size": {
                      "X": 449.0,
                      "Y": 64.0
                    },
                    "Name": "Image_1",
                    "ctype": "ImageViewObjectData"
                  },
                  {
                    "FontSize": 28,
                    "LabelText": "报名参赛   ",
                    "FontResource": {
                      "Type": "Normal",
                      "Path": "fonts/lanting.TTF",
                      "Plist": ""
                    },
                    "OutlineColor": {
                      "G": 0,
                      "B": 0
                    },
                    "ShadowColor": {
                      "R": 110,
                      "G": 110,
                      "B": 110
                    },
                    "ShadowOffsetX": 2.0,
                    "ShadowOffsetY": -2.0,
                    "AnchorPoint": {
                      "ScaleX": 0.5,
                      "ScaleY": 0.5
                    },
                    "Position": {
                      "X": 467.0,
                      "Y": 461.32
                    },
                    "Scale": {
                      "ScaleX": 1.0,
                      "ScaleY": 1.0
                    },
                    "CColor": {},
                    "IconVisible": false,
                    "PositionPercentXEnabled": true,
                    "PrePosition": {
                      "X": 0.5,
                      "Y": 0.919
                    },
                    "PreSize": {
                      "X": 0.137,
                      "Y": 0.0637
                    },
                    "LeftMargin": 403.0,
                    "RightMargin": 403.0,
                    "TopMargin": 24.68,
                    "BottomMargin": 445.32,
                    "Tag": 1705,
                    "ActionTag": -1484815513,
                    "Size": {
                      "X": 128.0,
                      "Y": 32.0
                    },
                    "Name": "Text_1",
                    "ctype": "TextObjectData"
                  }
                ],
                "ActionTag": -779001714,
                "Size": {
                  "X": 934.0,
                  "Y": 502.0
                },
                "Name": "bg",
                "ctype": "ImageViewObjectData"
              },
              {
                "FileData": {
                  "Type": "Normal",
                  "Path": "friendCards/common/suizi.png",
                  "Plist": ""
                },
                "Scale9OriginX": 6,
                "Scale9OriginY": 81,
                "Scale9Width": 7,
                "Scale9Height": 85,
                "AnchorPoint": {
                  "ScaleX": 0.5,
                  "ScaleY": 1.0
                },
                "Position": {
                  "X": 1079.7822,
                  "Y": 430.614
                },
                "Scale": {
                  "ScaleX": 1.0,
                  "ScaleY": 1.0
                },
                "CColor": {},
                "IconVisible": false,
                "PrePosition": {
                  "X": 0.8436,
                  "Y": 0.5981
                },
                "PreSize": {
                  "X": 0.0148,
                  "Y": 0.3431
                },
                "LeftMargin": 1070.2822,
                "RightMargin": 190.7178,
                "TopMargin": 289.386,
                "BottomMargin": 183.614,
                "Tag": 95,
                "ActionTag": 436270227,
                "Size": {
                  "X": 19.0,
                  "Y": 247.0
                },
                "Name": "suizi",
                "ctype": "ImageViewObjectData"
              },
              {
                "FontSize": 14,
                "ButtonText": "",
                "TextColor": {
                  "R": 65,
                  "G": 65,
                  "B": 70
                },
                "DisabledFileData": {
                  "Type": "Normal",
                  "Path": "friendCards/common/btn_close1_s.png",
                  "Plist": ""
                },
                "PressedFileData": {
                  "Type": "Normal",
                  "Path": "friendCards/common/btn_close1_s.png",
                  "Plist": ""
                },
                "NormalFileData": {
                  "Type": "Normal",
                  "Path": "friendCards/common/btn_close1_n.png",
                  "Plist": ""
                },
                "Scale9Enable": true,
                "Scale9OriginX": 15,
                "Scale9OriginY": 11,
                "Scale9Width": 122,
                "Scale9Height": 139,
                "OutlineColor": {
                  "G": 0,
                  "B": 0
                },
                "ShadowColor": {
                  "R": 110,
                  "G": 110,
                  "B": 110
                },
                "ShadowOffsetX": 2.0,
                "ShadowOffsetY": -2.0,
                "TouchEnable": true,
                "AnchorPoint": {
                  "ScaleX": 0.5,
                  "ScaleY": 0.5
                },
                "Position": {
                  "X": 1075.7031,
                  "Y": 443.2433
                },
                "Scale": {
                  "ScaleX": 1.0,
                  "ScaleY": 1.0
                },
                "CColor": {},
                "IconVisible": false,
                "PrePosition": {
                  "X": 0.8404,
                  "Y": 0.6156
                },
                "PreSize": {
                  "X": 0.1187,
                  "Y": 0.2236
                },
                "LeftMargin": 999.7031,
                "RightMargin": 128.2969,
                "TopMargin": 196.2567,
                "BottomMargin": 362.7433,
                "Tag": 94,
                "ActionTag": 693048896,
                "Size": {
                  "X": 152.0,
                  "Y": 161.0
                },
                "Name": "btn_close",
                "ctype": "ButtonObjectData"
              },
              {
                "DirectionType": "Vertical",
                "IsBounceEnabled": true,
                "ScrollDirectionType": 0,
                "ClipAble": true,
                "BackColorAlpha": 0,
                "ComboBoxIndex": 1,
                "SingleColor": {
                  "R": 150,
                  "G": 150
                },
                "FirstColor": {
                  "R": 150,
                  "G": 150
                },
                "EndColor": {},
                "ColorVector": {
                  "ScaleY": 1.0
                },
                "Scale9Width": 1,
                "Scale9Height": 1,
                "TouchEnable": true,
                "AnchorPoint": {
                  "ScaleX": 0.5,
                  "ScaleY": 0.5
                },
                "Position": {
                  "X": 640.0,
                  "Y": 335.7961
                },
                "Scale": {
                  "ScaleX": 1.0,
                  "ScaleY": 1.0
                },
                "CColor": {},
                "IconVisible": false,
                "PositionPercentXEnabled": true,
                "PrePosition": {
                  "X": 0.5,
                  "Y": 0.4664
                },
                "PercentWidthEnable": true,
                "PercentHeightEnable": true,
                "PercentWidthEnabled": true,
                "PercentHeightEnabled": true,
                "PreSize": {
                  "X": 0.58,
                  "Y": 0.55
                },
                "LeftMargin": 268.8,
                "RightMargin": 268.8,
                "TopMargin": 186.2039,
                "BottomMargin": 137.7961,
                "Tag": 1706,
                "ActionTag": 793813464,
                "Size": {
                  "X": 742.4,
                  "Y": 396.0
                },
                "Name": "ListView_1",
                "ctype": "ListViewObjectData"
              },
              {
                "FontSize": 32,
                "LabelText": "暂无可报名比赛，请联系会长配置！",
                "FontResource": {
                  "Type": "Normal",
                  "Path": "fonts/lanting.TTF",
                  "Plist": ""
                },
                "OutlineColor": {
                  "G": 0,
                  "B": 0
                },
                "ShadowColor": {
                  "R": 110,
                  "G": 110,
                  "B": 110
                },
                "ShadowOffsetX": 2.0,
                "ShadowOffsetY": -2.0,
                "AnchorPoint": {
                  "ScaleX": 0.5,
                  "ScaleY": 0.5
                },
                "Position": {
                  "X": 640.0,
                  "Y": 349.4196
                },
                "Scale": {
                  "ScaleX": 1.0,
                  "ScaleY": 1.0
                },
                "CColor": {
                  "R": 0,
                  "G": 0,
                  "B": 0
                },
                "IconVisible": false,
                "PositionPercentXEnabled": true,
                "PrePosition": {
                  "X": 0.5,
                  "Y": 0.4853
                },
                "PreSize": {
                  "X": 0.3852,
                  "Y": 0.0514
                },
                "LeftMargin": 393.5,
                "RightMargin": 393.5,
                "TopMargin": 352.0804,
                "BottomMargin": 330.9196,
                "Tag": 500,
                "ActionTag": -1754766839,
                "Size": {
                  "X": 493.0,
                  "Y": 37.0
                },
                "Name": "Text_null",
                "ctype": "TextObjectData"
              },
              {
                "ClipAble": false,
                "BackColorAlpha": 0,
                "ComboBoxIndex": 1,
                "SingleColor": {
                  "R": 150,
                  "G": 200
                },
                "FirstColor": {
                  "R": 150,
                  "G": 200
                },
                "EndColor": {},
                "ColorVector": {
                  "ScaleY": 1.0
                },
                "Scale9OriginX": -233,
                "Scale9OriginY": -30,
                "Scale9Width": 466,
                "Scale9Height": 60,
                "TouchEnable": true,
                "AnchorPoint": {},
                "Position": {
                  "X": 269.056,
                  "Y": 411.9856
                },
                "Scale": {
                  "ScaleX": 1.0,
                  "ScaleY": 1.0
                },
                "CColor": {},
                "IconVisible": false,
                "PositionPercentXEnabled": true,
                "PrePosition": {
                  "X": 0.2102,
                  "Y": 0.5722
                },
                "PercentWidthEnable": true,
                "PercentWidthEnabled": true,
                "PreSize": {
                  "X": 0.58,
                  "Y": 0.15
                },
                "LeftMargin": 269.056,
                "RightMargin": 268.5441,
                "TopMargin": 200.0144,
                "BottomMargin": 411.9856,
                "Tag": 1709,
                "Children": [
                  {
                    "FileData": {
                      "Type": "Normal",
                      "Path": "friendCards_Match/bg_joinMatch.png",
                      "Plist": ""
                    },
                    "Scale9Enable": true,
                    "Scale9OriginX": 233,
                    "Scale9OriginY": 30,
                    "Scale9Width": 241,
                    "Scale9Height": 31,
                    "AnchorPoint": {
                      "ScaleX": 0.5,
                      "ScaleY": 0.5
                    },
                    "Position": {
                      "X": 371.2,
                      "Y": 54.0
                    },
                    "Scale": {
                      "ScaleX": 1.0,
                      "ScaleY": 1.0
                    },
                    "CColor": {},
                    "IconVisible": false,
                    "PositionPercentXEnabled": true,
                    "PositionPercentYEnabled": true,
                    "PrePosition": {
                      "X": 0.5,
                      "Y": 0.5
                    },
                    "PercentWidthEnable": true,
                    "PercentWidthEnabled": true,
                    "PreSize": {
                      "X": 1.0,
                      "Y": 0.8426
                    },
                    "RightMargin": -0.0001,
                    "TopMargin": 8.5,
                    "BottomMargin": 8.5,
                    "Tag": 1710,
                    "ActionTag": -2076962453,
                    "Size": {
                      "X": 742.4,
                      "Y": 91.0
                    },
                    "Name": "Image_2",
                    "ctype": "ImageViewObjectData"
                  },
                  {
                    "FontSize": 20,
                    "LabelText": "时长：   ",
                    "FontResource": {
                      "Type": "Normal",
                      "Path": "fonts/lanting.TTF",
                      "Plist": ""
                    },
                    "OutlineColor": {
                      "G": 0,
                      "B": 0
                    },
                    "ShadowColor": {
                      "R": 110,
                      "G": 110,
                      "B": 110
                    },
                    "ShadowOffsetX": 2.0,
                    "ShadowOffsetY": -2.0,
                    "AnchorPoint": {
                      "ScaleY": 0.5
                    },
                    "Position": {
                      "X": 230.8309,
                      "Y": 67.8901
                    },
                    "Scale": {
                      "ScaleX": 1.0,
                      "ScaleY": 1.0
                    },
                    "CColor": {
                      "R": 68,
                      "G": 51,
                      "B": 51
                    },
                    "IconVisible": false,
                    "PrePosition": {
                      "X": 0.3109,
                      "Y": 0.6286
                    },
                    "PreSize": {
                      "X": 0.097,
                      "Y": 0.213
                    },
                    "LeftMargin": 230.8309,
                    "RightMargin": 439.5691,
                    "TopMargin": 28.6099,
                    "BottomMargin": 56.3901,
                    "Tag": 1712,
                    "ActionTag": -79985144,
                    "Size": {
                      "X": 72.0,
                      "Y": 23.0
                    },
                    "Name": "Text_title_matchTime",
                    "ctype": "TextObjectData"
                  },
                  {
                    "FontSize": 24,
                    "LabelText": "比赛名称比赛名称",
                    "FontResource": {
                      "Type": "Normal",
                      "Path": "fonts/lanting.TTF",
                      "Plist": ""
                    },
                    "OutlineColor": {
                      "G": 0,
                      "B": 0
                    },
                    "ShadowColor": {
                      "R": 110,
                      "G": 110,
                      "B": 110
                    },
                    "ShadowOffsetX": 2.0,
                    "ShadowOffsetY": -2.0,
                    "AnchorPoint": {
                      "ScaleY": 0.5
                    },
                    "Position": {
                      "X": 18.624,
                      "Y": 54.0
                    },
                    "Scale": {
                      "ScaleX": 1.0,
                      "ScaleY": 1.0
                    },
                    "CColor": {
                      "R": 68,
                      "G": 51,
                      "B": 51
                    },
                    "IconVisible": false,
                    "PositionPercentYEnabled": true,
                    "PrePosition": {
                      "X": 0.0251,
                      "Y": 0.5
                    },
                    "PreSize": {
                      "X": 0.2627,
                      "Y": 0.25
                    },
                    "LeftMargin": 18.624,
                    "RightMargin": 528.776,
                    "TopMargin": 40.5,
                    "BottomMargin": 40.5,
                    "Tag": 105,
                    "ActionTag": 1512571379,
                    "Size": {
                      "X": 195.0,
                      "Y": 27.0
                    },
                    "Name": "Text_matchName",
                    "ctype": "TextObjectData"
                  },
                  {
                    "IsCustomSize": true,
                    "FontSize": 20,
                    "LabelText": "1949.10.01-2019.10.01     ",
                    "FontResource": {
                      "Type": "Normal",
                      "Path": "fonts/lanting.TTF",
                      "Plist": ""
                    },
                    "OutlineColor": {
                      "G": 0,
                      "B": 0
                    },
                    "ShadowColor": {
                      "R": 110,
                      "G": 110,
                      "B": 110
                    },
                    "ShadowOffsetX": 2.0,
                    "ShadowOffsetY": -2.0,
                    "AnchorPoint": {
                      "ScaleY": 0.5
                    },
                    "Position": {
                      "X": 283.4243,
                      "Y": 67.8901
                    },
                    "Scale": {
                      "ScaleX": 1.0,
                      "ScaleY": 1.0
                    },
                    "CColor": {
                      "R": 211,
                      "G": 38,
                      "B": 14
                    },
                    "IconVisible": false,
                    "PrePosition": {
                      "X": 0.3818,
                      "Y": 0.6286
                    },
                    "PreSize": {
                      "X": 0.3408,
                      "Y": 0.213
                    },
                    "LeftMargin": 283.4243,
                    "RightMargin": 205.9756,
                    "TopMargin": 28.6099,
                    "BottomMargin": 56.3901,
                    "Tag": 108,
                    "ActionTag": -1659073959,
                    "Size": {
                      "X": 253.0,
                      "Y": 23.0
                    },
                    "Name": "Text_matchTime",
                    "ctype": "TextObjectData"
                  },
                  {
                    "FontSize": 20,
                    "LabelText": "参赛起始分:",
                    "FontResource": {
                      "Type": "Normal",
                      "Path": "fonts/lanting.TTF",
                      "Plist": ""
                    },
                    "OutlineColor": {
                      "G": 0,
                      "B": 0
                    },
                    "ShadowColor": {
                      "R": 110,
                      "G": 110,
                      "B": 110
                    },
                    "ShadowOffsetX": 2.0,
                    "ShadowOffsetY": -2.0,
                    "AnchorPoint": {
                      "ScaleY": 0.5
                    },
                    "Position": {
                      "X": 230.8309,
                      "Y": 32.6524
                    },
                    "Scale": {
                      "ScaleX": 1.0,
                      "ScaleY": 1.0
                    },
                    "CColor": {
                      "R": 68,
                      "G": 51,
                      "B": 51
                    },
                    "IconVisible": false,
                    "PrePosition": {
                      "X": 0.3109,
                      "Y": 0.3023
                    },
                    "PreSize": {
                      "X": 0.1455,
                      "Y": 0.213
                    },
                    "LeftMargin": 230.8309,
                    "RightMargin": 403.5691,
                    "TopMargin": 63.8476,
                    "BottomMargin": 21.1524,
                    "Tag": 65,
                    "ActionTag": -1448885241,
                    "Size": {
                      "X": 108.0,
                      "Y": 23.0
                    },
                    "Name": "Text_title_score",
                    "ctype": "TextObjectData"
                  },
                  {
                    "IsCustomSize": true,
                    "FontSize": 20,
                    "LabelText": "1000000000000",
                    "FontResource": {
                      "Type": "Normal",
                      "Path": "fonts/lanting.TTF",
                      "Plist": ""
                    },
                    "OutlineColor": {
                      "G": 0,
                      "B": 0
                    },
                    "ShadowColor": {
                      "R": 110,
                      "G": 110,
                      "B": 110
                    },
                    "ShadowOffsetX": 2.0,
                    "ShadowOffsetY": -2.0,
                    "AnchorPoint": {
                      "ScaleY": 0.5
                    },
                    "Position": {
                      "X": 342.226,
                      "Y": 32.6524
                    },
                    "Scale": {
                      "ScaleX": 1.0,
                      "ScaleY": 1.0
                    },
                    "CColor": {
                      "R": 211,
                      "G": 38,
                      "B": 14
                    },
                    "IconVisible": false,
                    "PrePosition": {
                      "X": 0.461,
                      "Y": 0.3023
                    },
                    "PreSize": {
                      "X": 0.2142,
                      "Y": 0.213
                    },
                    "LeftMargin": 342.226,
                    "RightMargin": 241.174,
                    "TopMargin": 63.8476,
                    "BottomMargin": 21.1524,
                    "Tag": 66,
                    "ActionTag": -225753618,
                    "Size": {
                      "X": 159.0,
                      "Y": 23.0
                    },
                    "Name": "Text_score",
                    "ctype": "TextObjectData"
                  },
                  {
                    "FontSize": 26,
                    "LabelText": "免费",
                    "FontResource": {
                      "Type": "Normal",
                      "Path": "fonts/lanting.TTF",
                      "Plist": ""
                    },
                    "OutlineColor": {
                      "G": 0,
                      "B": 0
                    },
                    "ShadowColor": {
                      "R": 110,
                      "G": 110,
                      "B": 110
                    },
                    "ShadowOffsetX": 2.0,
                    "ShadowOffsetY": -2.0,
                    "AnchorPoint": {
                      "ScaleY": 0.5
                    },
                    "Position": {
                      "X": 530.5933,
                      "Y": 54.0
                    },
                    "Scale": {
                      "ScaleX": 1.0,
                      "ScaleY": 1.0
                    },
                    "CColor": {
                      "R": 68,
                      "G": 51,
                      "B": 51
                    },
                    "IconVisible": false,
                    "PositionPercentXEnabled": true,
                    "PositionPercentYEnabled": true,
                    "PrePosition": {
                      "X": 0.7147,
                      "Y": 0.5
                    },
                    "PreSize": {
                      "X": 0.0727,
                      "Y": 0.2778
                    },
                    "LeftMargin": 530.5933,
                    "RightMargin": 157.8067,
                    "TopMargin": 39.0,
                    "BottomMargin": 39.0,
                    "Tag": 67,
                    "ActionTag": 2102492380,
                    "Size": {
                      "X": 54.0,
                      "Y": 30.0
                    },
                    "Name": "Text_payment",
                    "ctype": "TextObjectData"
                  },
                  {
                    "FontSize": 14,
                    "ButtonText": "",
                    "TextColor": {
                      "R": 65,
                      "G": 65,
                      "B": 70
                    },
                    "NormalFileData": {
                      "Type": "Normal",
                      "Path": "friendCards_Match/btn_sign.png",
                      "Plist": ""
                    },
                    "Scale9Enable": true,
                    "Scale9OriginX": 15,
                    "Scale9OriginY": 11,
                    "Scale9Width": 99,
                    "Scale9Height": 28,
                    "OutlineColor": {
                      "G": 0,
                      "B": 0
                    },
                    "ShadowColor": {
                      "R": 110,
                      "G": 110,
                      "B": 110
                    },
                    "ShadowOffsetX": 2.0,
                    "ShadowOffsetY": -2.0,
                    "TouchEnable": true,
                    "AnchorPoint": {
                      "ScaleX": 0.5,
                      "ScaleY": 0.5
                    },
                    "Position": {
                      "X": 663.9788,
                      "Y": 54.0
                    },
                    "Scale": {
                      "ScaleX": 1.0,
                      "ScaleY": 1.0
                    },
                    "CColor": {},
                    "IconVisible": false,
                    "PositionPercentYEnabled": true,
                    "PrePosition": {
                      "X": 0.8944,
                      "Y": 0.5
                    },
                    "PreSize": {
                      "X": 0.1738,
                      "Y": 0.463
                    },
                    "LeftMargin": 599.4788,
                    "RightMargin": 13.9211,
                    "TopMargin": 29.0,
                    "BottomMargin": 29.0,
                    "Tag": 68,
                    "ActionTag": 295889320,
                    "Size": {
                      "X": 129.0,
                      "Y": 50.0
                    },
                    "Name": "btn_sign",
                    "ctype": "ButtonObjectData"
                  }
                ],
                "ActionTag": 1607171021,
                "Size": {
                  "X": 742.4,
                  "Y": 108.0
                },
                "Name": "Panel_1",
                "ctype": "PanelObjectData"
              }
            ],
            "ActionTag": -49758235,
            "Size": {
              "X": 1280.0,
              "Y": 720.0
            },
            "Name": "back",
            "ctype": "PanelObjectData"
          }
        ],
        "Size": {
          "X": 0.0,
          "Y": 0.0
        },
        "Name": "Node",
        "ctype": "SingleNodeObjectData"
      },
      "UsedResources": [
        "fonts/lanting.TTF",
        "friendCards/common/btn_close1_n.png",
        "friendCards/common/btn_close1_s.png",
        "friendCards/common/img_xiaotanchuang.png",
        "friendCards/common/suizi.png",
        "friendCards/common/titel_2.png",
        "friendCards_Match/bg_joinMatch.png",
        "friendCards_Match/btn_sign.png"
      ],
      "ctype": "GameFileData"
    }
  },
  "Type": "Node"
}