{
  "ID": "6f62dfe7-c818-4876-8192-04713c6cdb8a",
  "Version": "2.3.4",
  "Name": "friendcard_FCM_setting",
  "Content": {
    "Content": {
      "Animation": {
        "Duration": 0,
        "Speed": 1.0,
        "Timelines": [],
        "ctype": "TimelineActionData"
      },
      "AnimationList": [],
      "ObjectData": {
        "Tag": 134,
        "Children": [
          {
            "ClipAble": false,
            "ComboBoxIndex": 1,
            "SingleColor": {
              "R": 0,
              "G": 0,
              "B": 0
            },
            "FirstColor": {
              "R": 150,
              "G": 200
            },
            "EndColor": {},
            "ColorVector": {
              "ScaleY": 1.0
            },
            "Scale9Width": 1,
            "Scale9Height": 1,
            "TouchEnable": true,
            "AnchorPoint": {
              "ScaleX": 0.5,
              "ScaleY": 0.5
            },
            "Position": {
              "X": 640.0,
              "Y": 360.0
            },
            "Scale": {
              "ScaleX": 1.0,
              "ScaleY": 1.0
            },
            "CColor": {
              "R": 0,
              "G": 0,
              "B": 0
            },
            "IconVisible": false,
            "PositionPercentXEnabled": true,
            "PositionPercentYEnabled": true,
            "PrePosition": {
              "X": 0.5,
              "Y": 0.5
            },
            "PreSize": {
              "X": 1.0,
              "Y": 1.0
            },
            "Tag": 460,
            "ActionTag": 1393860366,
            "Size": {
              "X": 1280.0,
              "Y": 720.0
            },
            "Alpha": 153,
            "Name": "Image_di",
            "ctype": "PanelObjectData"
          },
          {
            "ClipAble": false,
            "BackColorAlpha": 0,
            "ComboBoxIndex": 1,
            "SingleColor": {
              "R": 150,
              "G": 200
            },
            "FirstColor": {
              "R": 150,
              "G": 200
            },
            "EndColor": {},
            "ColorVector": {
              "ScaleY": 1.0
            },
            "Scale9Width": 1,
            "Scale9Height": 1,
            "TouchEnable": true,
            "AnchorPoint": {
              "ScaleX": 0.5,
              "ScaleY": 0.5
            },
            "Position": {
              "X": 640.0,
              "Y": 360.0
            },
            "Scale": {
              "ScaleX": 1.0,
              "ScaleY": 1.0
            },
            "CColor": {},
            "IconVisible": false,
            "PositionPercentXEnabled": true,
            "PositionPercentYEnabled": true,
            "PrePosition": {
              "X": 0.5,
              "Y": 0.5
            },
            "PreSize": {
              "X": 1.0,
              "Y": 1.0
            },
            "Tag": 436,
            "Children": [
              {
                "FileData": {
                  "Type": "Normal",
                  "Path": "friendCards/common/img_zhongtanchuang2.png",
                  "Plist": ""
                },
                "Scale9OriginX": 121,
                "Scale9OriginY": 197,
                "Scale9Width": 979,
                "Scale9Height": 269,
                "TouchEnable": true,
                "AnchorPoint": {
                  "ScaleX": 0.5,
                  "ScaleY": 0.5
                },
                "Position": {
                  "X": 640.0,
                  "Y": 360.0
                },
                "Scale": {
                  "ScaleX": 1.0,
                  "ScaleY": 1.0
                },
                "CColor": {},
                "IconVisible": false,
                "PositionPercentXEnabled": true,
                "PositionPercentYEnabled": true,
                "PrePosition": {
                  "X": 0.5,
                  "Y": 0.5
                },
                "PreSize": {
                  "X": 0.9539,
                  "Y": 0.9208
                },
                "LeftMargin": 29.5,
                "RightMargin": 29.5,
                "TopMargin": 28.5,
                "BottomMargin": 28.5,
                "Tag": 404,
                "ActionTag": 1633824306,
                "Size": {
                  "X": 1221.0,
                  "Y": 663.0
                },
                "Name": "bgImage",
                "ctype": "ImageViewObjectData"
              },
              {
                "FileData": {
                  "Type": "Normal",
                  "Path": "friendCards/common/img_dikuang.png",
                  "Plist": ""
                },
                "Scale9Enable": true,
                "Scale9OriginX": 22,
                "Scale9OriginY": 21,
                "Scale9Width": 6,
                "Scale9Height": 8,
                "AnchorPoint": {
                  "ScaleX": 0.5,
                  "ScaleY": 1.0
                },
                "Position": {
                  "X": 639.9999,
                  "Y": 560.9089
                },
                "Scale": {
                  "ScaleX": 1.0,
                  "ScaleY": 1.0
                },
                "CColor": {},
                "IconVisible": false,
                "PrePosition": {
                  "X": 0.5,
                  "Y": 0.779
                },
                "PreSize": {
                  "X": 0.718,
                  "Y": 0.5556
                },
                "LeftMargin": 180.4999,
                "RightMargin": 180.5001,
                "TopMargin": 159.0911,
                "BottomMargin": 160.9089,
                "Tag": 162,
                "ActionTag": 1502161066,
                "Size": {
                  "X": 919.0,
                  "Y": 400.0
                },
                "Name": "diImage",
                "ctype": "ImageViewObjectData"
              },
              {
                "FontSize": 28,
                "LabelText": " 防沉迷 ",
                "FontResource": {
                  "Type": "Normal",
                  "Path": "fonts/lanting.TTF",
                  "Plist": ""
                },
                "OutlineColor": {
                  "G": 0,
                  "B": 0
                },
                "ShadowColor": {
                  "R": 110,
                  "G": 110,
                  "B": 110
                },
                "ShadowOffsetX": 2.0,
                "ShadowOffsetY": -2.0,
                "AnchorPoint": {
                  "ScaleX": 0.5,
                  "ScaleY": 0.5
                },
                "Position": {
                  "X": 236.01,
                  "Y": 591.58
                },
                "Scale": {
                  "ScaleX": 1.0,
                  "ScaleY": 1.0
                },
                "CColor": {
                  "R": 0,
                  "G": 0,
                  "B": 0
                },
                "IconVisible": false,
                "PrePosition": {
                  "X": 0.1844,
                  "Y": 0.8216
                },
                "PreSize": {
                  "X": 0.0742,
                  "Y": 0.0444
                },
                "LeftMargin": 188.51,
                "RightMargin": 996.49,
                "TopMargin": 112.42,
                "BottomMargin": 575.58,
                "Tag": 287,
                "ActionTag": 170877010,
                "Size": {
                  "X": 95.0,
                  "Y": 32.0
                },
                "Name": "text2",
                "ctype": "TextObjectData"
              },
              {
                "CheckedState": true,
                "NormalBackFileData": {
                  "Type": "Normal",
                  "Path": "friendCards/nvguanjia/checkBox_close.png",
                  "Plist": ""
                },
                "PressedBackFileData": {
                  "Type": "Normal",
                  "Path": "friendCards/nvguanjia/checkBox_close.png",
                  "Plist": ""
                },
                "NodeNormalFileData": {
                  "Type": "Normal",
                  "Path": "friendCards/nvguanjia/checkBox_open.png",
                  "Plist": ""
                },
                "NodeDisableFileData": {
                  "Type": "Normal",
                  "Path": "friendCards/nvguanjia/checkBox_open.png",
                  "Plist": ""
                },
                "TouchEnable": true,
                "AnchorPoint": {
                  "ScaleX": 0.5,
                  "ScaleY": 0.5
                },
                "Position": {
                  "X": 340.62,
                  "Y": 591.58
                },
                "Scale": {
                  "ScaleX": 1.0,
                  "ScaleY": 1.0
                },
                "CColor": {},
                "IconVisible": false,
                "PrePosition": {
                  "X": 0.2661,
                  "Y": 0.8216
                },
                "PreSize": {
                  "X": 0.082,
                  "Y": 0.0528
                },
                "LeftMargin": 288.12,
                "RightMargin": 886.88,
                "TopMargin": 109.42,
                "BottomMargin": 572.58,
                "Tag": 772,
                "ActionTag": 737230679,
                "Size": {
                  "X": 105.0,
                  "Y": 38.0
                },
                "Name": "openCheckBox",
                "ctype": "CheckBoxObjectData"
              },
              {
                "FontSize": 28,
                "LabelText": "  说明：玩家初始防沉迷分数为0，重置后的值都为0  ",
                "FontResource": {
                  "Type": "Normal",
                  "Path": "fonts/lanting.TTF",
                  "Plist": ""
                },
                "OutlineColor": {
                  "G": 0,
                  "B": 0
                },
                "ShadowColor": {
                  "R": 110,
                  "G": 110,
                  "B": 110
                },
                "ShadowOffsetX": 2.0,
                "ShadowOffsetY": -2.0,
                "AnchorPoint": {
                  "ScaleX": 0.5,
                  "ScaleY": 0.5
                },
                "Position": {
                  "X": 543.87,
                  "Y": 499.95
                },
                "Scale": {
                  "ScaleX": 1.0,
                  "ScaleY": 1.0
                },
                "CColor": {
                  "R": 68,
                  "G": 51,
                  "B": 51
                },
                "IconVisible": false,
                "PrePosition": {
                  "X": 0.4249,
                  "Y": 0.6944
                },
                "PreSize": {
                  "X": 0.5047,
                  "Y": 0.0444
                },
                "LeftMargin": 220.87,
                "RightMargin": 413.13,
                "TopMargin": 204.05,
                "BottomMargin": 483.95,
                "Tag": 2092,
                "ActionTag": 670394040,
                "Size": {
                  "X": 646.0,
                  "Y": 32.0
                },
                "Name": "text1",
                "ctype": "TextObjectData"
              },
              {
                "FileData": {
                  "Type": "Normal",
                  "Path": "friendCards/common/img_hengxian.png",
                  "Plist": ""
                },
                "Scale9OriginX": 263,
                "Scale9Width": 271,
                "Scale9Height": 2,
                "AnchorPoint": {
                  "ScaleX": 0.5,
                  "ScaleY": 0.5
                },
                "Position": {
                  "X": 640.0,
                  "Y": 466.9994
                },
                "Scale": {
                  "ScaleX": 1.0,
                  "ScaleY": 1.0
                },
                "CColor": {},
                "IconVisible": false,
                "PositionPercentXEnabled": true,
                "PrePosition": {
                  "X": 0.5,
                  "Y": 0.6486
                },
                "PreSize": {
                  "X": 0.6227,
                  "Y": 0.0028
                },
                "LeftMargin": 241.5,
                "RightMargin": 241.5,
                "TopMargin": 252.0006,
                "BottomMargin": 465.9994,
                "Tag": 404,
                "ActionTag": 1393254152,
                "Size": {
                  "X": 797.0,
                  "Y": 2.0
                },
                "Name": "line1",
                "ctype": "ImageViewObjectData"
              },
              {
                "CheckedState": true,
                "NormalBackFileData": {
                  "Type": "Normal",
                  "Path": "friendCards/common/btn_chebox_fang.png",
                  "Plist": ""
                },
                "PressedBackFileData": {
                  "Type": "Normal",
                  "Path": "friendCards/common/btn_chebox_fang.png",
                  "Plist": ""
                },
                "DisableBackFileData": {
                  "Type": "Normal",
                  "Path": "friendCards/common/btn_chebox_fang.png",
                  "Plist": ""
                },
                "NodeNormalFileData": {
                  "Type": "Normal",
                  "Path": "friendCards/common/img_gou.png",
                  "Plist": ""
                },
                "NodeDisableFileData": {
                  "Type": "Normal",
                  "Path": "friendCards/common/btn_chebox_fang.png",
                  "Plist": ""
                },
                "TouchEnable": true,
                "AnchorPoint": {
                  "ScaleX": 0.5,
                  "ScaleY": 0.5
                },
                "Position": {
                  "X": 255.6658,
                  "Y": 414.0518
                },
                "Scale": {
                  "ScaleX": 1.0,
                  "ScaleY": 1.0
                },
                "CColor": {},
                "IconVisible": false,
                "PrePosition": {
                  "X": 0.1997,
                  "Y": 0.5751
                },
                "PreSize": {
                  "X": 0.0281,
                  "Y": 0.0486
                },
                "LeftMargin": 237.6658,
                "RightMargin": 1006.3342,
                "TopMargin": 288.4482,
                "BottomMargin": 396.5518,
                "Tag": 407,
                "Children": [
                  {
                    "FontSize": 28,
                    "LabelText": " 当玩家防沉迷分数达到 ",
                    "FontResource": {
                      "Type": "Normal",
                      "Path": "fonts/lanting.TTF",
                      "Plist": ""
                    },
                    "OutlineColor": {
                      "G": 0,
                      "B": 0
                    },
                    "ShadowColor": {
                      "R": 110,
                      "G": 110,
                      "B": 110
                    },
                    "ShadowOffsetX": 2.0,
                    "ShadowOffsetY": -2.0,
                    "AnchorPoint": {
                      "ScaleY": 0.5
                    },
                    "Position": {
                      "X": 40.0,
                      "Y": 17.5
                    },
                    "Scale": {
                      "ScaleX": 1.0,
                      "ScaleY": 1.0
                    },
                    "CColor": {
                      "R": 68,
                      "G": 51,
                      "B": 51
                    },
                    "IconVisible": false,
                    "PositionPercentYEnabled": true,
                    "PrePosition": {
                      "X": 1.1111,
                      "Y": 0.5
                    },
                    "PreSize": {
                      "X": 8.0556,
                      "Y": 0.9143
                    },
                    "LeftMargin": 40.0,
                    "RightMargin": -294.0,
                    "TopMargin": 1.5,
                    "BottomMargin": 1.5,
                    "Tag": 408,
                    "ActionTag": -1637094142,
                    "Size": {
                      "X": 290.0,
                      "Y": 32.0
                    },
                    "Name": "text",
                    "ctype": "TextObjectData"
                  }
                ],
                "ActionTag": 282984189,
                "Size": {
                  "X": 36.0,
                  "Y": 35.0
                },
                "Name": "checkBox1",
                "ctype": "CheckBoxObjectData"
              },
              {
                "FileData": {
                  "Type": "Normal",
                  "Path": "friendCards/common/img_dikuang.png",
                  "Plist": ""
                },
                "Scale9Enable": true,
                "Scale9OriginX": 22,
                "Scale9OriginY": 12,
                "Scale9Width": 6,
                "Scale9Height": 26,
                "TouchEnable": true,
                "AnchorPoint": {
                  "ScaleX": 0.5,
                  "ScaleY": 0.5
                },
                "Position": {
                  "X": 670.7808,
                  "Y": 414.0472
                },
                "Scale": {
                  "ScaleX": 1.0,
                  "ScaleY": 1.0
                },
                "CColor": {},
                "IconVisible": false,
                "PrePosition": {
                  "X": 0.524,
                  "Y": 0.5751
                },
                "PreSize": {
                  "X": 0.1406,
                  "Y": 0.0736
                },
                "LeftMargin": 580.7808,
                "RightMargin": 519.2192,
                "TopMargin": 279.4528,
                "BottomMargin": 387.5472,
                "Tag": 1059,
                "Children": [
                  {
                    "FontSize": 14,
                    "ButtonText": "",
                    "TextColor": {
                      "R": 65,
                      "G": 65,
                      "B": 70
                    },
                    "DisabledFileData": {
                      "Type": "Normal",
                      "Path": "friendCards/memberManage/jiantou1.png",
                      "Plist": ""
                    },
                    "PressedFileData": {
                      "Type": "Normal",
                      "Path": "friendCards/memberManage/jiantou1.png",
                      "Plist": ""
                    },
                    "NormalFileData": {
                      "Type": "Normal",
                      "Path": "friendCards/memberManage/jiantou2.png",
                      "Plist": ""
                    },
                    "Scale9Enable": true,
                    "Scale9OriginX": 15,
                    "Scale9OriginY": 11,
                    "Scale9Width": 4,
                    "Scale9Height": 12,
                    "OutlineColor": {
                      "G": 0,
                      "B": 0
                    },
                    "ShadowColor": {
                      "R": 110,
                      "G": 110,
                      "B": 110
                    },
                    "ShadowOffsetX": 2.0,
                    "ShadowOffsetY": -2.0,
                    "AnchorPoint": {
                      "ScaleX": 0.5,
                      "ScaleY": 0.5
                    },
                    "Position": {
                      "X": 155.1002,
                      "Y": 26.5
                    },
                    "Scale": {
                      "ScaleX": 1.0,
                      "ScaleY": 1.0
                    },
                    "CColor": {},
                    "IconVisible": false,
                    "PositionPercentYEnabled": true,
                    "PrePosition": {
                      "X": 0.8617,
                      "Y": 0.5
                    },
                    "PreSize": {
                      "X": 0.1889,
                      "Y": 0.6415
                    },
                    "LeftMargin": 138.1002,
                    "RightMargin": 7.8998,
                    "TopMargin": 9.5,
                    "BottomMargin": 9.5,
                    "Tag": 1060,
                    "ActionTag": 343034707,
                    "Size": {
                      "X": 34.0,
                      "Y": 34.0
                    },
                    "Name": "Button_jiaotou",
                    "ctype": "ButtonObjectData"
                  },
                  {
                    "FontSize": 26,
                    "LabelText": "10",
                    "FontResource": {
                      "Type": "Normal",
                      "Path": "fonts/lanting.TTF",
                      "Plist": ""
                    },
                    "OutlineColor": {
                      "G": 0,
                      "B": 0
                    },
                    "ShadowColor": {
                      "R": 110,
                      "G": 110,
                      "B": 110
                    },
                    "ShadowOffsetX": 2.0,
                    "ShadowOffsetY": -2.0,
                    "AnchorPoint": {
                      "ScaleX": 0.5,
                      "ScaleY": 0.5
                    },
                    "Position": {
                      "X": 81.2,
                      "Y": 25.1856
                    },
                    "Scale": {
                      "ScaleX": 1.0,
                      "ScaleY": 1.0
                    },
                    "CColor": {
                      "R": 211,
                      "G": 38,
                      "B": 14
                    },
                    "IconVisible": false,
                    "PositionPercentYEnabled": true,
                    "PrePosition": {
                      "X": 0.4511,
                      "Y": 0.4752
                    },
                    "PreSize": {
                      "X": 0.1889,
                      "Y": 0.566
                    },
                    "LeftMargin": 64.2,
                    "RightMargin": 81.8,
                    "TopMargin": 12.8144,
                    "BottomMargin": 10.1856,
                    "Tag": 1061,
                    "ActionTag": 1771580420,
                    "Size": {
                      "X": 34.0,
                      "Y": 30.0
                    },
                    "Name": "text",
                    "ctype": "TextObjectData"
                  }
                ],
                "ActionTag": -784701795,
                "Size": {
                  "X": 180.0,
                  "Y": 53.0
                },
                "Name": "selectNode1",
                "ctype": "ImageViewObjectData"
              },
              {
                "FontSize": 28,
                "LabelText": " 禁止玩牌",
                "FontResource": {
                  "Type": "Normal",
                  "Path": "fonts/lanting.TTF",
                  "Plist": ""
                },
                "OutlineColor": {
                  "G": 0,
                  "B": 0
                },
                "ShadowColor": {
                  "R": 110,
                  "G": 110,
                  "B": 110
                },
                "ShadowOffsetX": 2.0,
                "ShadowOffsetY": -2.0,
                "AnchorPoint": {
                  "ScaleX": 0.5,
                  "ScaleY": 0.5
                },
                "Position": {
                  "X": 835.072,
                  "Y": 414.0512
                },
                "Scale": {
                  "ScaleX": 1.0,
                  "ScaleY": 1.0
                },
                "CColor": {
                  "R": 68,
                  "G": 51,
                  "B": 51
                },
                "IconVisible": false,
                "PositionPercentXEnabled": true,
                "PrePosition": {
                  "X": 0.6524,
                  "Y": 0.5751
                },
                "PreSize": {
                  "X": 0.0953,
                  "Y": 0.0444
                },
                "LeftMargin": 774.072,
                "RightMargin": 383.928,
                "TopMargin": 289.9488,
                "BottomMargin": 398.0512,
                "Tag": 409,
                "ActionTag": 1232545554,
                "Size": {
                  "X": 122.0,
                  "Y": 32.0
                },
                "Name": "text",
                "ctype": "TextObjectData"
              },
              {
                "FileData": {
                  "Type": "Normal",
                  "Path": "friendCards/common/img_hengxian.png",
                  "Plist": ""
                },
                "Scale9OriginX": 263,
                "Scale9Width": 271,
                "Scale9Height": 2,
                "AnchorPoint": {
                  "ScaleX": 0.5,
                  "ScaleY": 0.5
                },
                "Position": {
                  "X": 640.0,
                  "Y": 381.4984
                },
                "Scale": {
                  "ScaleX": 1.0,
                  "ScaleY": 1.0
                },
                "CColor": {},
                "IconVisible": false,
                "PositionPercentXEnabled": true,
                "PrePosition": {
                  "X": 0.5,
                  "Y": 0.5299
                },
                "PreSize": {
                  "X": 0.6227,
                  "Y": 0.0028
                },
                "LeftMargin": 241.5,
                "RightMargin": 241.5,
                "TopMargin": 337.5016,
                "BottomMargin": 380.4984,
                "Tag": 405,
                "ActionTag": -1775894551,
                "Size": {
                  "X": 797.0,
                  "Y": 2.0
                },
                "Name": "line2",
                "ctype": "ImageViewObjectData"
              },
              {
                "CheckedState": true,
                "NormalBackFileData": {
                  "Type": "Normal",
                  "Path": "friendCards/common/btn_chebox_fang.png",
                  "Plist": ""
                },
                "PressedBackFileData": {
                  "Type": "Normal",
                  "Path": "friendCards/common/btn_chebox_fang.png",
                  "Plist": ""
                },
                "DisableBackFileData": {
                  "Type": "Normal",
                  "Path": "friendCards/common/btn_chebox_fang.png",
                  "Plist": ""
                },
                "NodeNormalFileData": {
                  "Type": "Normal",
                  "Path": "friendCards/common/img_gou.png",
                  "Plist": ""
                },
                "NodeDisableFileData": {
                  "Type": "Normal",
                  "Path": "friendCards/common/btn_chebox_fang.png",
                  "Plist": ""
                },
                "TouchEnable": true,
                "AnchorPoint": {
                  "ScaleX": 0.5,
                  "ScaleY": 0.5
                },
                "Position": {
                  "X": 255.6651,
                  "Y": 325.9401
                },
                "Scale": {
                  "ScaleX": 1.0,
                  "ScaleY": 1.0
                },
                "CColor": {},
                "IconVisible": false,
                "PrePosition": {
                  "X": 0.1997,
                  "Y": 0.4527
                },
                "PreSize": {
                  "X": 0.0281,
                  "Y": 0.0486
                },
                "LeftMargin": 237.6651,
                "RightMargin": 1006.3349,
                "TopMargin": 376.5599,
                "BottomMargin": 308.4401,
                "Tag": 1051,
                "Children": [
                  {
                    "FontSize": 28,
                    "LabelText": " 一天内玩家游戏时长高于 ",
                    "FontResource": {
                      "Type": "Normal",
                      "Path": "fonts/lanting.TTF",
                      "Plist": ""
                    },
                    "OutlineColor": {
                      "G": 0,
                      "B": 0
                    },
                    "ShadowColor": {
                      "R": 110,
                      "G": 110,
                      "B": 110
                    },
                    "ShadowOffsetX": 2.0,
                    "ShadowOffsetY": -2.0,
                    "AnchorPoint": {
                      "ScaleY": 0.5
                    },
                    "Position": {
                      "X": 40.0,
                      "Y": 17.5
                    },
                    "Scale": {
                      "ScaleX": 1.0,
                      "ScaleY": 1.0
                    },
                    "CColor": {
                      "R": 68,
                      "G": 51,
                      "B": 51
                    },
                    "IconVisible": false,
                    "PositionPercentYEnabled": true,
                    "PrePosition": {
                      "X": 1.1111,
                      "Y": 0.5
                    },
                    "PreSize": {
                      "X": 8.8333,
                      "Y": 0.9143
                    },
                    "LeftMargin": 40.0,
                    "RightMargin": -322.0,
                    "TopMargin": 1.5,
                    "BottomMargin": 1.5,
                    "Tag": 1052,
                    "ActionTag": 1673540719,
                    "Size": {
                      "X": 318.0,
                      "Y": 32.0
                    },
                    "Name": "text",
                    "ctype": "TextObjectData"
                  }
                ],
                "ActionTag": -198706287,
                "Size": {
                  "X": 36.0,
                  "Y": 35.0
                },
                "Name": "checkBox2",
                "ctype": "CheckBoxObjectData"
              },
              {
                "FileData": {
                  "Type": "Normal",
                  "Path": "friendCards/common/img_dikuang.png",
                  "Plist": ""
                },
                "Scale9Enable": true,
                "Scale9OriginX": 22,
                "Scale9OriginY": 12,
                "Scale9Width": 6,
                "Scale9Height": 26,
                "TouchEnable": true,
                "AnchorPoint": {
                  "ScaleX": 0.5,
                  "ScaleY": 0.5
                },
                "Position": {
                  "X": 694.083,
                  "Y": 325.9401
                },
                "Scale": {
                  "ScaleX": 1.0,
                  "ScaleY": 1.0
                },
                "CColor": {},
                "IconVisible": false,
                "PrePosition": {
                  "X": 0.5423,
                  "Y": 0.4527
                },
                "PreSize": {
                  "X": 0.1406,
                  "Y": 0.0736
                },
                "LeftMargin": 604.083,
                "RightMargin": 495.917,
                "TopMargin": 367.5599,
                "BottomMargin": 299.4401,
                "Tag": 1062,
                "Children": [
                  {
                    "FontSize": 14,
                    "ButtonText": "",
                    "TextColor": {
                      "R": 65,
                      "G": 65,
                      "B": 70
                    },
                    "DisabledFileData": {
                      "Type": "Normal",
                      "Path": "friendCards/memberManage/jiantou1.png",
                      "Plist": ""
                    },
                    "PressedFileData": {
                      "Type": "Normal",
                      "Path": "friendCards/memberManage/jiantou1.png",
                      "Plist": ""
                    },
                    "NormalFileData": {
                      "Type": "Normal",
                      "Path": "friendCards/memberManage/jiantou2.png",
                      "Plist": ""
                    },
                    "Scale9Enable": true,
                    "Scale9OriginX": 15,
                    "Scale9OriginY": 11,
                    "Scale9Width": 4,
                    "Scale9Height": 12,
                    "OutlineColor": {
                      "G": 0,
                      "B": 0
                    },
                    "ShadowColor": {
                      "R": 110,
                      "G": 110,
                      "B": 110
                    },
                    "ShadowOffsetX": 2.0,
                    "ShadowOffsetY": -2.0,
                    "AnchorPoint": {
                      "ScaleX": 0.5,
                      "ScaleY": 0.5
                    },
                    "Position": {
                      "X": 155.1002,
                      "Y": 26.5
                    },
                    "Scale": {
                      "ScaleX": 1.0,
                      "ScaleY": 1.0
                    },
                    "CColor": {},
                    "IconVisible": false,
                    "PositionPercentYEnabled": true,
                    "PrePosition": {
                      "X": 0.8617,
                      "Y": 0.5
                    },
                    "PreSize": {
                      "X": 0.1889,
                      "Y": 0.6415
                    },
                    "LeftMargin": 138.1002,
                    "RightMargin": 7.8998,
                    "TopMargin": 9.5,
                    "BottomMargin": 9.5,
                    "Tag": 1063,
                    "ActionTag": 1836037097,
                    "Size": {
                      "X": 34.0,
                      "Y": 34.0
                    },
                    "Name": "Button_jiaotou",
                    "ctype": "ButtonObjectData"
                  },
                  {
                    "FontSize": 26,
                    "LabelText": "10",
                    "FontResource": {
                      "Type": "Normal",
                      "Path": "fonts/lanting.TTF",
                      "Plist": ""
                    },
                    "OutlineColor": {
                      "G": 0,
                      "B": 0
                    },
                    "ShadowColor": {
                      "R": 110,
                      "G": 110,
                      "B": 110
                    },
                    "ShadowOffsetX": 2.0,
                    "ShadowOffsetY": -2.0,
                    "AnchorPoint": {
                      "ScaleX": 0.5,
                      "ScaleY": 0.5
                    },
                    "Position": {
                      "X": 81.2,
                      "Y": 25.1856
                    },
                    "Scale": {
                      "ScaleX": 1.0,
                      "ScaleY": 1.0
                    },
                    "CColor": {
                      "R": 211,
                      "G": 38,
                      "B": 14
                    },
                    "IconVisible": false,
                    "PositionPercentYEnabled": true,
                    "PrePosition": {
                      "X": 0.4511,
                      "Y": 0.4752
                    },
                    "PreSize": {
                      "X": 0.1889,
                      "Y": 0.566
                    },
                    "LeftMargin": 64.2,
                    "RightMargin": 81.8,
                    "TopMargin": 12.8144,
                    "BottomMargin": 10.1856,
                    "Tag": 1064,
                    "ActionTag": 1408305635,
                    "Size": {
                      "X": 34.0,
                      "Y": 30.0
                    },
                    "Name": "text",
                    "ctype": "TextObjectData"
                  }
                ],
                "ActionTag": -238754577,
                "Size": {
                  "X": 180.0,
                  "Y": 53.0
                },
                "Name": "selectNode2",
                "ctype": "ImageViewObjectData"
              },
              {
                "FontSize": 28,
                "LabelText": " 禁止玩牌",
                "FontResource": {
                  "Type": "Normal",
                  "Path": "fonts/lanting.TTF",
                  "Plist": ""
                },
                "OutlineColor": {
                  "G": 0,
                  "B": 0
                },
                "ShadowColor": {
                  "R": 110,
                  "G": 110,
                  "B": 110
                },
                "ShadowOffsetX": 2.0,
                "ShadowOffsetY": -2.0,
                "AnchorPoint": {
                  "ScaleX": 0.5,
                  "ScaleY": 0.5
                },
                "Position": {
                  "X": 856.832,
                  "Y": 325.9401
                },
                "Scale": {
                  "ScaleX": 1.0,
                  "ScaleY": 1.0
                },
                "CColor": {
                  "R": 68,
                  "G": 51,
                  "B": 51
                },
                "IconVisible": false,
                "PositionPercentXEnabled": true,
                "PrePosition": {
                  "X": 0.6694,
                  "Y": 0.4527
                },
                "PreSize": {
                  "X": 0.0953,
                  "Y": 0.0444
                },
                "LeftMargin": 795.832,
                "RightMargin": 362.168,
                "TopMargin": 378.0599,
                "BottomMargin": 309.9401,
                "Tag": 1053,
                "ActionTag": -481363196,
                "Size": {
                  "X": 122.0,
                  "Y": 32.0
                },
                "Name": "text2",
                "ctype": "TextObjectData"
              },
              {
                "FileData": {
                  "Type": "Normal",
                  "Path": "friendCards/common/img_hengxian.png",
                  "Plist": ""
                },
                "Scale9OriginX": 263,
                "Scale9Width": 271,
                "Scale9Height": 2,
                "AnchorPoint": {
                  "ScaleX": 0.5,
                  "ScaleY": 0.5
                },
                "Position": {
                  "X": 640.0,
                  "Y": 295.9975
                },
                "Scale": {
                  "ScaleX": 1.0,
                  "ScaleY": 1.0
                },
                "CColor": {},
                "IconVisible": false,
                "PositionPercentXEnabled": true,
                "PrePosition": {
                  "X": 0.5,
                  "Y": 0.4111
                },
                "PreSize": {
                  "X": 0.6227,
                  "Y": 0.0028
                },
                "LeftMargin": 241.5,
                "RightMargin": 241.5,
                "TopMargin": 423.0025,
                "BottomMargin": 294.9975,
                "Tag": 1054,
                "ActionTag": 1175492239,
                "Size": {
                  "X": 797.0,
                  "Y": 2.0
                },
                "Name": "line3",
                "ctype": "ImageViewObjectData"
              },
              {
                "CheckedState": true,
                "NormalBackFileData": {
                  "Type": "Normal",
                  "Path": "friendCards/common/btn_chebox_fang.png",
                  "Plist": ""
                },
                "PressedBackFileData": {
                  "Type": "Normal",
                  "Path": "friendCards/common/btn_chebox_fang.png",
                  "Plist": ""
                },
                "DisableBackFileData": {
                  "Type": "Normal",
                  "Path": "friendCards/common/btn_chebox_fang.png",
                  "Plist": ""
                },
                "NodeNormalFileData": {
                  "Type": "Normal",
                  "Path": "friendCards/common/img_gou.png",
                  "Plist": ""
                },
                "NodeDisableFileData": {
                  "Type": "Normal",
                  "Path": "friendCards/common/btn_chebox_fang.png",
                  "Plist": ""
                },
                "TouchEnable": true,
                "AnchorPoint": {
                  "ScaleX": 0.5,
                  "ScaleY": 0.5
                },
                "Position": {
                  "X": 255.6648,
                  "Y": 249.4727
                },
                "Scale": {
                  "ScaleX": 1.0,
                  "ScaleY": 1.0
                },
                "CColor": {},
                "IconVisible": false,
                "PrePosition": {
                  "X": 0.1997,
                  "Y": 0.3465
                },
                "PreSize": {
                  "X": 0.0281,
                  "Y": 0.0486
                },
                "LeftMargin": 237.6648,
                "RightMargin": 1006.3352,
                "TopMargin": 453.0273,
                "BottomMargin": 231.9727,
                "Tag": 1055,
                "Children": [
                  {
                    "FontSize": 28,
                    "LabelText": " 一天内玩家对局场次高于 ",
                    "FontResource": {
                      "Type": "Normal",
                      "Path": "fonts/lanting.TTF",
                      "Plist": ""
                    },
                    "OutlineColor": {
                      "G": 0,
                      "B": 0
                    },
                    "ShadowColor": {
                      "R": 110,
                      "G": 110,
                      "B": 110
                    },
                    "ShadowOffsetX": 2.0,
                    "ShadowOffsetY": -2.0,
                    "AnchorPoint": {
                      "ScaleY": 0.5
                    },
                    "Position": {
                      "X": 40.0,
                      "Y": 17.5
                    },
                    "Scale": {
                      "ScaleX": 1.0,
                      "ScaleY": 1.0
                    },
                    "CColor": {
                      "R": 68,
                      "G": 51,
                      "B": 51
                    },
                    "IconVisible": false,
                    "PositionPercentYEnabled": true,
                    "PrePosition": {
                      "X": 1.1111,
                      "Y": 0.5
                    },
                    "PreSize": {
                      "X": 8.8333,
                      "Y": 0.9143
                    },
                    "LeftMargin": 40.0,
                    "RightMargin": -322.0,
                    "TopMargin": 1.5,
                    "BottomMargin": 1.5,
                    "Tag": 1056,
                    "ActionTag": -2073267182,
                    "Size": {
                      "X": 318.0,
                      "Y": 32.0
                    },
                    "Name": "text",
                    "ctype": "TextObjectData"
                  }
                ],
                "ActionTag": -341845025,
                "Size": {
                  "X": 36.0,
                  "Y": 35.0
                },
                "Name": "checkBox3",
                "ctype": "CheckBoxObjectData"
              },
              {
                "FileData": {
                  "Type": "Normal",
                  "Path": "friendCards/common/img_dikuang.png",
                  "Plist": ""
                },
                "Scale9Enable": true,
                "Scale9OriginX": 22,
                "Scale9OriginY": 12,
                "Scale9Width": 6,
                "Scale9Height": 26,
                "TouchEnable": true,
                "AnchorPoint": {
                  "ScaleX": 0.5,
                  "ScaleY": 0.5
                },
                "Position": {
                  "X": 694.2897,
                  "Y": 250.0291
                },
                "Scale": {
                  "ScaleX": 1.0,
                  "ScaleY": 1.0
                },
                "CColor": {},
                "IconVisible": false,
                "PrePosition": {
                  "X": 0.5424,
                  "Y": 0.3473
                },
                "PreSize": {
                  "X": 0.1406,
                  "Y": 0.0736
                },
                "LeftMargin": 604.2897,
                "RightMargin": 495.7103,
                "TopMargin": 443.4709,
                "BottomMargin": 223.5291,
                "Tag": 1065,
                "Children": [
                  {
                    "FontSize": 14,
                    "ButtonText": "",
                    "TextColor": {
                      "R": 65,
                      "G": 65,
                      "B": 70
                    },
                    "DisabledFileData": {
                      "Type": "Normal",
                      "Path": "friendCards/memberManage/jiantou1.png",
                      "Plist": ""
                    },
                    "PressedFileData": {
                      "Type": "Normal",
                      "Path": "friendCards/memberManage/jiantou1.png",
                      "Plist": ""
                    },
                    "NormalFileData": {
                      "Type": "Normal",
                      "Path": "friendCards/memberManage/jiantou2.png",
                      "Plist": ""
                    },
                    "Scale9Enable": true,
                    "Scale9OriginX": 15,
                    "Scale9OriginY": 11,
                    "Scale9Width": 4,
                    "Scale9Height": 12,
                    "OutlineColor": {
                      "G": 0,
                      "B": 0
                    },
                    "ShadowColor": {
                      "R": 110,
                      "G": 110,
                      "B": 110
                    },
                    "ShadowOffsetX": 2.0,
                    "ShadowOffsetY": -2.0,
                    "AnchorPoint": {
                      "ScaleX": 0.5,
                      "ScaleY": 0.5
                    },
                    "Position": {
                      "X": 155.1002,
                      "Y": 26.5
                    },
                    "Scale": {
                      "ScaleX": 1.0,
                      "ScaleY": 1.0
                    },
                    "CColor": {},
                    "IconVisible": false,
                    "PositionPercentYEnabled": true,
                    "PrePosition": {
                      "X": 0.8617,
                      "Y": 0.5
                    },
                    "PreSize": {
                      "X": 0.1889,
                      "Y": 0.6415
                    },
                    "LeftMargin": 138.1002,
                    "RightMargin": 7.8998,
                    "TopMargin": 9.5,
                    "BottomMargin": 9.5,
                    "Tag": 1066,
                    "ActionTag": -553432887,
                    "Size": {
                      "X": 34.0,
                      "Y": 34.0
                    },
                    "Name": "Button_jiaotou",
                    "ctype": "ButtonObjectData"
                  },
                  {
                    "FontSize": 26,
                    "LabelText": "10",
                    "FontResource": {
                      "Type": "Normal",
                      "Path": "fonts/lanting.TTF",
                      "Plist": ""
                    },
                    "OutlineColor": {
                      "G": 0,
                      "B": 0
                    },
                    "ShadowColor": {
                      "R": 110,
                      "G": 110,
                      "B": 110
                    },
                    "ShadowOffsetX": 2.0,
                    "ShadowOffsetY": -2.0,
                    "AnchorPoint": {
                      "ScaleX": 0.5,
                      "ScaleY": 0.5
                    },
                    "Position": {
                      "X": 81.2,
                      "Y": 25.1856
                    },
                    "Scale": {
                      "ScaleX": 1.0,
                      "ScaleY": 1.0
                    },
                    "CColor": {
                      "R": 211,
                      "G": 38,
                      "B": 14
                    },
                    "IconVisible": false,
                    "PositionPercentYEnabled": true,
                    "PrePosition": {
                      "X": 0.4511,
                      "Y": 0.4752
                    },
                    "PreSize": {
                      "X": 0.1889,
                      "Y": 0.566
                    },
                    "LeftMargin": 64.2,
                    "RightMargin": 81.8,
                    "TopMargin": 12.8144,
                    "BottomMargin": 10.1856,
                    "Tag": 1067,
                    "ActionTag": 1572494609,
                    "Size": {
                      "X": 34.0,
                      "Y": 30.0
                    },
                    "Name": "text",
                    "ctype": "TextObjectData"
                  }
                ],
                "ActionTag": 1215014558,
                "Size": {
                  "X": 180.0,
                  "Y": 53.0
                },
                "Name": "selectNode3",
                "ctype": "ImageViewObjectData"
              },
              {
                "FontSize": 28,
                "LabelText": " 禁止玩牌",
                "FontResource": {
                  "Type": "Normal",
                  "Path": "fonts/lanting.TTF",
                  "Plist": ""
                },
                "OutlineColor": {
                  "G": 0,
                  "B": 0
                },
                "ShadowColor": {
                  "R": 110,
                  "G": 110,
                  "B": 110
                },
                "ShadowOffsetX": 2.0,
                "ShadowOffsetY": -2.0,
                "AnchorPoint": {
                  "ScaleX": 0.5,
                  "ScaleY": 0.5
                },
                "Position": {
                  "X": 856.832,
                  "Y": 249.4738
                },
                "Scale": {
                  "ScaleX": 1.0,
                  "ScaleY": 1.0
                },
                "CColor": {
                  "R": 68,
                  "G": 51,
                  "B": 51
                },
                "IconVisible": false,
                "PositionPercentXEnabled": true,
                "PrePosition": {
                  "X": 0.6694,
                  "Y": 0.3465
                },
                "PreSize": {
                  "X": 0.0953,
                  "Y": 0.0444
                },
                "LeftMargin": 795.832,
                "RightMargin": 362.168,
                "TopMargin": 454.5262,
                "BottomMargin": 233.4738,
                "Tag": 1057,
                "ActionTag": -350705439,
                "Size": {
                  "X": 122.0,
                  "Y": 32.0
                },
                "Name": "text3",
                "ctype": "TextObjectData"
              },
              {
                "FontSize": 14,
                "ButtonText": "",
                "TextColor": {
                  "R": 65,
                  "G": 65,
                  "B": 70
                },
                "DisabledFileData": {
                  "Type": "Default",
                  "Path": "Default/Button_Disable.png",
                  "Plist": ""
                },
                "NormalFileData": {
                  "Type": "Normal",
                  "Path": "friendCards_FCM/setting/baocun_n.png",
                  "Plist": ""
                },
                "Scale9Enable": true,
                "Scale9OriginX": 15,
                "Scale9OriginY": 11,
                "Scale9Width": 141,
                "Scale9Height": 44,
                "OutlineColor": {
                  "G": 0,
                  "B": 0
                },
                "ShadowColor": {
                  "R": 110,
                  "G": 110,
                  "B": 110
                },
                "ShadowOffsetX": 2.0,
                "ShadowOffsetY": -2.0,
                "TouchEnable": true,
                "AnchorPoint": {
                  "ScaleX": 0.5,
                  "ScaleY": 0.5
                },
                "Position": {
                  "X": 638.976,
                  "Y": 109.2
                },
                "Scale": {
                  "ScaleX": 1.0,
                  "ScaleY": 1.0
                },
                "CColor": {},
                "IconVisible": false,
                "PositionPercentXEnabled": true,
                "PrePosition": {
                  "X": 0.4992,
                  "Y": 0.1517
                },
                "PreSize": {
                  "X": 0.1336,
                  "Y": 0.0917
                },
                "LeftMargin": 553.476,
                "RightMargin": 555.524,
                "TopMargin": 577.8,
                "BottomMargin": 76.2,
                "Tag": 434,
                "ActionTag": -1733581979,
                "Size": {
                  "X": 171.0,
                  "Y": 66.0
                },
                "Name": "saveBtn",
                "ctype": "ButtonObjectData"
              },
              {
                "FileData": {
                  "Type": "Normal",
                  "Path": "common/suizi.png",
                  "Plist": ""
                },
                "Scale9OriginX": 6,
                "Scale9OriginY": 81,
                "Scale9Width": 7,
                "Scale9Height": 85,
                "AnchorPoint": {
                  "ScaleX": 0.5,
                  "ScaleY": 1.0
                },
                "Position": {
                  "X": 1198.5601,
                  "Y": 521.1183
                },
                "Scale": {
                  "ScaleX": 1.0,
                  "ScaleY": 1.0
                },
                "CColor": {},
                "IconVisible": false,
                "PrePosition": {
                  "X": 0.9364,
                  "Y": 0.7238
                },
                "PreSize": {
                  "X": 0.0148,
                  "Y": 0.3431
                },
                "LeftMargin": 1189.0601,
                "RightMargin": 71.9399,
                "TopMargin": 198.8817,
                "BottomMargin": 274.1183,
                "Tag": 354,
                "ActionTag": -1858872973,
                "Size": {
                  "X": 19.0,
                  "Y": 247.0
                },
                "Name": "suizi",
                "ctype": "ImageViewObjectData"
              },
              {
                "FontSize": 14,
                "ButtonText": "",
                "TextColor": {
                  "R": 65,
                  "G": 65,
                  "B": 70
                },
                "PressedFileData": {
                  "Type": "Normal",
                  "Path": "friendCards/common/btn_close1_s.png",
                  "Plist": ""
                },
                "NormalFileData": {
                  "Type": "Normal",
                  "Path": "friendCards/common/btn_close1_n.png",
                  "Plist": ""
                },
                "Scale9Enable": true,
                "Scale9OriginX": 15,
                "Scale9OriginY": 11,
                "Scale9Width": 122,
                "Scale9Height": 139,
                "OutlineColor": {
                  "G": 0,
                  "B": 0
                },
                "ShadowColor": {
                  "R": 110,
                  "G": 110,
                  "B": 110
                },
                "ShadowOffsetX": 2.0,
                "ShadowOffsetY": -2.0,
                "TouchEnable": true,
                "AnchorPoint": {
                  "ScaleX": 0.4075,
                  "ScaleY": 0.5784
                },
                "Position": {
                  "X": 1179.7913,
                  "Y": 544.907
                },
                "Scale": {
                  "ScaleX": 1.0,
                  "ScaleY": 1.0
                },
                "CColor": {},
                "IconVisible": false,
                "PrePosition": {
                  "X": 0.9217,
                  "Y": 0.7568
                },
                "PreSize": {
                  "X": 0.1187,
                  "Y": 0.2236
                },
                "LeftMargin": 1117.8513,
                "RightMargin": 10.1487,
                "TopMargin": 107.2155,
                "BottomMargin": 451.7846,
                "Tag": 353,
                "ActionTag": -405624565,
                "Size": {
                  "X": 152.0,
                  "Y": 161.0
                },
                "Name": "close",
                "ctype": "ButtonObjectData"
              },
              {
                "FontSize": 14,
                "ButtonText": "",
                "TextColor": {
                  "R": 65,
                  "G": 65,
                  "B": 70
                },
                "NormalFileData": {
                  "Type": "Normal",
                  "Path": "createNewPng/tip.png",
                  "Plist": ""
                },
                "Scale9OriginX": 15,
                "Scale9OriginY": 11,
                "Scale9Width": 16,
                "Scale9Height": 25,
                "OutlineColor": {
                  "G": 0,
                  "B": 0
                },
                "ShadowColor": {
                  "R": 110,
                  "G": 110,
                  "B": 110
                },
                "ShadowOffsetX": 2.0,
                "ShadowOffsetY": -2.0,
                "TouchEnable": true,
                "AnchorPoint": {
                  "ScaleX": 0.5,
                  "ScaleY": 0.5
                },
                "Position": {
                  "X": 1068.59,
                  "Y": 590.904
                },
                "Scale": {
                  "ScaleX": 1.0,
                  "ScaleY": 1.0
                },
                "CColor": {},
                "IconVisible": false,
                "PositionPercentYEnabled": true,
                "PrePosition": {
                  "X": 0.8348,
                  "Y": 0.8207
                },
                "PreSize": {
                  "X": 0.0359,
                  "Y": 0.0653
                },
                "LeftMargin": 1045.59,
                "RightMargin": 188.41,
                "TopMargin": 105.596,
                "BottomMargin": 567.404,
                "Tag": 1677,
                "ActionTag": 1607287403,
                "Size": {
                  "X": 46.0,
                  "Y": 47.0
                },
                "Name": "tipBtn",
                "ctype": "ButtonObjectData"
              },
              {
                "ClipAble": false,
                "BackColorAlpha": 102,
                "SingleColor": {
                  "R": 150,
                  "G": 200
                },
                "FirstColor": {
                  "R": 150,
                  "G": 200
                },
                "EndColor": {},
                "ColorVector": {
                  "ScaleY": 1.0
                },
                "Scale9Width": 1,
                "Scale9Height": 1,
                "TouchEnable": true,
                "AnchorPoint": {
                  "ScaleX": 0.5,
                  "ScaleY": 0.5
                },
                "Position": {
                  "X": 640.0,
                  "Y": 360.0
                },
                "Scale": {
                  "ScaleX": 1.0,
                  "ScaleY": 1.0
                },
                "CColor": {},
                "IconVisible": false,
                "PositionPercentXEnabled": true,
                "PositionPercentYEnabled": true,
                "PrePosition": {
                  "X": 0.5,
                  "Y": 0.5
                },
                "PreSize": {
                  "X": 0.1844,
                  "Y": 0.425
                },
                "LeftMargin": 522.0,
                "RightMargin": 522.0,
                "TopMargin": 207.0,
                "BottomMargin": 207.0,
                "Tag": 1068,
                "Children": [
                  {
                    "FileData": {
                      "Type": "Normal",
                      "Path": "friendCards/memberManage/bg_sort.png",
                      "Plist": ""
                    },
                    "Scale9Enable": true,
                    "Scale9OriginX": 73,
                    "Scale9OriginY": 136,
                    "Scale9Width": 77,
                    "Scale9Height": 143,
                    "AnchorPoint": {
                      "ScaleX": 0.5,
                      "ScaleY": 0.5
                    },
                    "Position": {
                      "X": 118.0,
                      "Y": 153.0
                    },
                    "Scale": {
                      "ScaleX": 1.0,
                      "ScaleY": 1.0
                    },
                    "CColor": {},
                    "IconVisible": false,
                    "PositionPercentXEnabled": true,
                    "PositionPercentYEnabled": true,
                    "PrePosition": {
                      "X": 0.5,
                      "Y": 0.5
                    },
                    "PercentWidthEnable": true,
                    "PercentHeightEnable": true,
                    "PercentWidthEnabled": true,
                    "PercentHeightEnabled": true,
                    "PreSize": {
                      "X": 1.0,
                      "Y": 1.0
                    },
                    "Tag": 1069,
                    "ActionTag": -212567072,
                    "Size": {
                      "X": 236.0,
                      "Y": 306.0
                    },
                    "Name": "di",
                    "ctype": "ImageViewObjectData"
                  },
                  {
                    "DirectionType": "Vertical",
                    "IsBounceEnabled": true,
                    "ScrollDirectionType": 0,
                    "ClipAble": true,
                    "BackColorAlpha": 102,
                    "SingleColor": {
                      "R": 150,
                      "G": 150
                    },
                    "FirstColor": {
                      "R": 150,
                      "G": 150
                    },
                    "EndColor": {},
                    "ColorVector": {
                      "ScaleY": 1.0
                    },
                    "Scale9Enable": true,
                    "Scale9OriginX": -113,
                    "Scale9OriginY": -96,
                    "Scale9Width": 226,
                    "Scale9Height": 192,
                    "TouchEnable": true,
                    "AnchorPoint": {
                      "ScaleX": 0.5,
                      "ScaleY": 0.5
                    },
                    "Position": {
                      "X": 118.0,
                      "Y": 153.0
                    },
                    "Scale": {
                      "ScaleX": 1.0,
                      "ScaleY": 1.0
                    },
                    "CColor": {},
                    "IconVisible": false,
                    "PositionPercentXEnabled": true,
                    "PositionPercentYEnabled": true,
                    "PrePosition": {
                      "X": 0.5,
                      "Y": 0.5
                    },
                    "PreSize": {
                      "X": 0.9746,
                      "Y": 0.9804
                    },
                    "LeftMargin": 3.0,
                    "RightMargin": 3.0,
                    "TopMargin": 3.0,
                    "BottomMargin": 3.0,
                    "Tag": 1070,
                    "ActionTag": -927249947,
                    "Size": {
                      "X": 230.0,
                      "Y": 300.0
                    },
                    "Name": "optionList",
                    "ctype": "ListViewObjectData"
                  },
                  {
                    "ClipAble": false,
                    "BackColorAlpha": 102,
                    "SingleColor": {
                      "R": 150,
                      "G": 200
                    },
                    "FirstColor": {
                      "R": 150,
                      "G": 200
                    },
                    "EndColor": {},
                    "ColorVector": {
                      "ScaleY": 1.0
                    },
                    "Scale9Width": 1,
                    "Scale9Height": 1,
                    "TouchEnable": true,
                    "AnchorPoint": {},
                    "Position": {
                      "X": 3.0,
                      "Y": 245.4506
                    },
                    "Scale": {
                      "ScaleX": 1.0,
                      "ScaleY": 1.0
                    },
                    "CColor": {},
                    "IconVisible": false,
                    "PrePosition": {
                      "X": 0.0127,
                      "Y": 0.8021
                    },
                    "PreSize": {
                      "X": 0.9746,
                      "Y": 0.1471
                    },
                    "LeftMargin": 3.0,
                    "RightMargin": 3.0,
                    "TopMargin": 15.5494,
                    "BottomMargin": 245.4506,
                    "Tag": 1071,
                    "Children": [
                      {
                        "FileData": {
                          "Type": "Normal",
                          "Path": "friendCards/memberManage/bg_sort_selected1.png",
                          "Plist": ""
                        },
                        "Scale9OriginX": 15,
                        "Scale9OriginY": 17,
                        "Scale9Width": 189,
                        "Scale9Height": 11,
                        "AnchorPoint": {
                          "ScaleX": 0.5,
                          "ScaleY": 0.5
                        },
                        "Position": {
                          "X": 115.0,
                          "Y": 22.5
                        },
                        "Scale": {
                          "ScaleX": 1.0,
                          "ScaleY": 1.0
                        },
                        "CColor": {},
                        "IconVisible": false,
                        "PositionPercentXEnabled": true,
                        "PositionPercentYEnabled": true,
                        "PrePosition": {
                          "X": 0.5,
                          "Y": 0.5
                        },
                        "PreSize": {
                          "X": 0.9522,
                          "Y": 1.0
                        },
                        "LeftMargin": 5.5,
                        "RightMargin": 5.5,
                        "Tag": 1072,
                        "ActionTag": -1770684143,
                        "Size": {
                          "X": 219.0,
                          "Y": 45.0
                        },
                        "Name": "Image_bg",
                        "ctype": "ImageViewObjectData"
                      },
                      {
                        "FontSize": 28,
                        "LabelText": "综合排序",
                        "FontResource": {
                          "Type": "Normal",
                          "Path": "fonts/lanting.TTF",
                          "Plist": ""
                        },
                        "OutlineColor": {
                          "G": 0,
                          "B": 0
                        },
                        "ShadowColor": {
                          "R": 110,
                          "G": 110,
                          "B": 110
                        },
                        "ShadowOffsetX": 2.0,
                        "ShadowOffsetY": -2.0,
                        "AnchorPoint": {
                          "ScaleY": 0.5
                        },
                        "Position": {
                          "X": 24.0,
                          "Y": 22.5
                        },
                        "Scale": {
                          "ScaleX": 1.0,
                          "ScaleY": 1.0
                        },
                        "CColor": {
                          "R": 43,
                          "G": 52,
                          "B": 76
                        },
                        "IconVisible": false,
                        "PositionPercentYEnabled": true,
                        "PrePosition": {
                          "X": 0.1043,
                          "Y": 0.5
                        },
                        "PreSize": {
                          "X": 0.4957,
                          "Y": 0.7111
                        },
                        "LeftMargin": 24.0,
                        "RightMargin": 92.0,
                        "TopMargin": 6.5,
                        "BottomMargin": 6.5,
                        "Tag": 1073,
                        "ActionTag": 1962381352,
                        "Size": {
                          "X": 114.0,
                          "Y": 32.0
                        },
                        "Name": "text",
                        "ctype": "TextObjectData"
                      },
                      {
                        "FileData": {
                          "Type": "Normal",
                          "Path": "friendCards/memberManage/sort_selected.png",
                          "Plist": ""
                        },
                        "Scale9OriginX": 11,
                        "Scale9OriginY": 11,
                        "Scale9Width": 14,
                        "Scale9Height": 10,
                        "AnchorPoint": {
                          "ScaleX": 0.5,
                          "ScaleY": 0.5
                        },
                        "Position": {
                          "X": 194.1,
                          "Y": 22.5
                        },
                        "Scale": {
                          "ScaleX": 1.0,
                          "ScaleY": 1.0
                        },
                        "CColor": {},
                        "IconVisible": false,
                        "PositionPercentYEnabled": true,
                        "PrePosition": {
                          "X": 0.8439,
                          "Y": 0.5
                        },
                        "PreSize": {
                          "X": 0.1565,
                          "Y": 0.8
                        },
                        "LeftMargin": 176.1,
                        "RightMargin": 17.9,
                        "TopMargin": 4.5,
                        "BottomMargin": 4.5,
                        "Tag": 1074,
                        "ActionTag": 1891886839,
                        "Size": {
                          "X": 36.0,
                          "Y": 36.0
                        },
                        "VisibleForFrame": false,
                        "Name": "Image_selected",
                        "ctype": "ImageViewObjectData"
                      },
                      {
                        "FileData": {
                          "Type": "Normal",
                          "Path": "friendCards/common/img_hengxian.png",
                          "Plist": ""
                        },
                        "Scale9OriginX": 263,
                        "Scale9Width": 271,
                        "Scale9Height": 2,
                        "AnchorPoint": {
                          "ScaleX": 0.5,
                          "ScaleY": 0.5
                        },
                        "Position": {
                          "X": 115.0,
                          "Y": 1.0
                        },
                        "Scale": {
                          "ScaleX": 1.0,
                          "ScaleY": 1.0
                        },
                        "CColor": {},
                        "IconVisible": false,
                        "PositionPercentXEnabled": true,
                        "PrePosition": {
                          "X": 0.5,
                          "Y": 0.0222
                        },
                        "PreSize": {
                          "X": 0.9565,
                          "Y": 0.0444
                        },
                        "LeftMargin": 5.0,
                        "RightMargin": 5.0,
                        "TopMargin": 43.0,
                        "Tag": 1075,
                        "ActionTag": -139422116,
                        "Size": {
                          "X": 220.0,
                          "Y": 2.0
                        },
                        "Name": "line",
                        "ctype": "ImageViewObjectData"
                      }
                    ],
                    "ActionTag": -1786767192,
                    "Size": {
                      "X": 230.0,
                      "Y": 45.0
                    },
                    "Name": "cell",
                    "ctype": "PanelObjectData"
                  }
                ],
                "ActionTag": 467807209,
                "Size": {
                  "X": 236.0,
                  "Y": 306.0
                },
                "VisibleForFrame": false,
                "Name": "optionNode",
                "ctype": "PanelObjectData"
              }
            ],
            "ActionTag": 1339648580,
            "Size": {
              "X": 1280.0,
              "Y": 720.0
            },
            "Name": "Panel",
            "ctype": "PanelObjectData"
          }
        ],
        "Size": {
          "X": 1280.0,
          "Y": 720.0
        },
        "Name": "Layer",
        "ctype": "LayerObjectData"
      },
      "UsedResources": [
        "common/suizi.png",
        "createNewPng/tip.png",
        "Default/Button_Disable.png",
        "fonts/lanting.TTF",
        "friendCards/common/btn_chebox_fang.png",
        "friendCards/common/btn_close1_n.png",
        "friendCards/common/btn_close1_s.png",
        "friendCards/common/img_dikuang.png",
        "friendCards/common/img_gou.png",
        "friendCards/common/img_hengxian.png",
        "friendCards/common/img_zhongtanchuang2.png",
        "friendCards/memberManage/bg_sort.png",
        "friendCards/memberManage/bg_sort_selected1.png",
        "friendCards/memberManage/jiantou1.png",
        "friendCards/memberManage/jiantou2.png",
        "friendCards/memberManage/sort_selected.png",
        "friendCards/nvguanjia/checkBox_close.png",
        "friendCards/nvguanjia/checkBox_open.png",
        "friendCards_FCM/setting/baocun_n.png"
      ],
      "ctype": "GameFileData"
    }
  },
  "Type": "Layer"
}