{
  "ID": "5d6bdc04-533b-42ca-81cf-0adf240412ec",
  "Version": "2.3.4",
  "Name": "ShopOfJiFen_info_3.0",
  "Content": {
    "Content": {
      "Animation": {
        "Duration": 0,
        "Speed": 1.0,
        "Timelines": [],
        "ctype": "TimelineActionData"
      },
      "AnimationList": [],
      "ObjectData": {
        "Tag": 195,
        "Children": [
          {
            "ClipAble": false,
            "BackColorAlpha": 153,
            "ComboBoxIndex": 1,
            "SingleColor": {
              "R": 0,
              "G": 0,
              "B": 0
            },
            "FirstColor": {
              "R": 150,
              "G": 200
            },
            "EndColor": {},
            "ColorVector": {
              "ScaleY": 1.0
            },
            "Scale9Width": 1,
            "Scale9Height": 1,
            "TouchEnable": true,
            "AnchorPoint": {
              "ScaleX": 0.5,
              "ScaleY": 0.5
            },
            "Position": {
              "X": 639.0,
              "Y": 360.0
            },
            "Scale": {
              "ScaleX": 1.0,
              "ScaleY": 1.0
            },
            "CColor": {},
            "IconVisible": false,
            "PrePosition": {
              "X": 0.4992,
              "Y": 0.5
            },
            "PreSize": {
              "X": 1.0,
              "Y": 1.0
            },
            "LeftMargin": -1.0,
            "RightMargin": 1.0,
            "Tag": 203,
            "ActionTag": 212976254,
            "Size": {
              "X": 1280.0,
              "Y": 720.0
            },
            "Name": "block",
            "ctype": "PanelObjectData"
          },
          {
            "ClipAble": false,
            "BackColorAlpha": 0,
            "ComboBoxIndex": 1,
            "SingleColor": {
              "R": 0,
              "G": 0,
              "B": 0
            },
            "FirstColor": {
              "R": 150,
              "G": 200
            },
            "EndColor": {},
            "ColorVector": {
              "ScaleY": 1.0
            },
            "Scale9Width": 1,
            "Scale9Height": 1,
            "AnchorPoint": {
              "ScaleX": 0.5,
              "ScaleY": 0.5
            },
            "Position": {
              "X": 640.0,
              "Y": 360.0
            },
            "Scale": {
              "ScaleX": 1.0,
              "ScaleY": 1.0
            },
            "CColor": {},
            "IconVisible": false,
            "PositionPercentXEnabled": true,
            "PositionPercentYEnabled": true,
            "PrePosition": {
              "X": 0.5,
              "Y": 0.5
            },
            "PreSize": {
              "X": 1.0,
              "Y": 1.0
            },
            "Tag": 892,
            "Children": [
              {
                "FileData": {
                  "Type": "Normal",
                  "Path": "common_3.0/bg_xiaokuang.png",
                  "Plist": ""
                },
                "Scale9Enable": true,
                "Scale9OriginX": 300,
                "Scale9OriginY": 61,
                "Scale9Width": 90,
                "Scale9Height": 16,
                "AnchorPoint": {
                  "ScaleX": 0.5,
                  "ScaleY": 0.5
                },
                "Position": {
                  "X": 640.0,
                  "Y": 360.0
                },
                "Scale": {
                  "ScaleX": 1.0,
                  "ScaleY": 1.0
                },
                "CColor": {},
                "IconVisible": false,
                "PositionPercentXEnabled": true,
                "PositionPercentYEnabled": true,
                "PrePosition": {
                  "X": 0.5,
                  "Y": 0.5
                },
                "PreSize": {
                  "X": 0.5391,
                  "Y": 0.8611
                },
                "LeftMargin": 295.0,
                "RightMargin": 295.0,
                "TopMargin": 50.0,
                "BottomMargin": 50.0,
                "Tag": 893,
                "Children": [
                  {
                    "FileData": {
                      "Type": "Normal",
                      "Path": "common_3.0/bg_dikuang.png",
                      "Plist": ""
                    },
                    "Scale9OriginX": 218,
                    "Scale9OriginY": 38,
                    "Scale9Width": 225,
                    "Scale9Height": 40,
                    "AnchorPoint": {
                      "ScaleX": 0.5,
                      "ScaleY": 0.5
                    },
                    "Position": {
                      "X": 345.0,
                      "Y": 75.2697
                    },
                    "Scale": {
                      "ScaleX": 1.0,
                      "ScaleY": 1.0
                    },
                    "CColor": {},
                    "IconVisible": false,
                    "PositionPercentXEnabled": true,
                    "PrePosition": {
                      "X": 0.5,
                      "Y": 0.1214
                    },
                    "PercentWidthEnable": true,
                    "PercentWidthEnabled": true,
                    "PreSize": {
                      "X": 0.95,
                      "Y": 0.1871
                    },
                    "LeftMargin": 17.25,
                    "RightMargin": 17.25,
                    "TopMargin": 486.7303,
                    "BottomMargin": 17.2697,
                    "Tag": 894,
                    "ActionTag": 1533812240,
                    "Size": {
                      "X": 655.5,
                      "Y": 116.0
                    },
                    "Name": "Image_14",
                    "ctype": "ImageViewObjectData"
                  }
                ],
                "ActionTag": -1593823613,
                "Size": {
                  "X": 690.0,
                  "Y": 620.0
                },
                "Name": "bg_1",
                "ctype": "ImageViewObjectData"
              },
              {
                "FileData": {
                  "Type": "Normal",
                  "Path": "ShopOfJiFen_3.0/tilte_duihuan.png",
                  "Plist": ""
                },
                "Scale9OriginX": 43,
                "Scale9OriginY": 10,
                "Scale9Width": 2,
                "Scale9Height": 17,
                "AnchorPoint": {
                  "ScaleX": 0.5,
                  "ScaleY": 0.5
                },
                "Position": {
                  "X": 640.0,
                  "Y": 640.6074
                },
                "Scale": {
                  "ScaleX": 1.0,
                  "ScaleY": 1.0
                },
                "CColor": {},
                "IconVisible": false,
                "PositionPercentXEnabled": true,
                "PrePosition": {
                  "X": 0.5,
                  "Y": 0.8897
                },
                "PreSize": {
                  "X": 0.0688,
                  "Y": 0.0514
                },
                "LeftMargin": 596.0,
                "RightMargin": 596.0,
                "TopMargin": 60.8926,
                "BottomMargin": 622.1074,
                "Tag": 895,
                "ActionTag": 846410802,
                "Size": {
                  "X": 88.0,
                  "Y": 37.0
                },
                "Name": "Image_6",
                "ctype": "ImageViewObjectData"
              },
              {
                "FontSize": 34,
                "ButtonText": "分享并兑换",
                "FontResource": {
                  "Type": "Normal",
                  "Path": "fonts/lanting.TTF",
                  "Plist": ""
                },
                "TextColor": {},
                "NormalFileData": {
                  "Type": "Normal",
                  "Path": "common_3.0/btn_lv.png",
                  "Plist": ""
                },
                "Scale9Enable": true,
                "Scale9OriginX": 15,
                "Scale9OriginY": 11,
                "Scale9Width": 188,
                "Scale9Height": 55,
                "OutlineColor": {
                  "G": 0,
                  "B": 0
                },
                "ShadowColor": {
                  "R": 110,
                  "G": 110,
                  "B": 110
                },
                "ShadowOffsetX": 2.0,
                "ShadowOffsetY": -2.0,
                "TouchEnable": true,
                "AnchorPoint": {
                  "ScaleX": 0.5,
                  "ScaleY": 0.5
                },
                "Position": {
                  "X": 640.0,
                  "Y": 111.2542
                },
                "Scale": {
                  "ScaleX": 1.0,
                  "ScaleY": 1.0
                },
                "CColor": {},
                "IconVisible": false,
                "PositionPercentXEnabled": true,
                "PrePosition": {
                  "X": 0.5,
                  "Y": 0.1545
                },
                "PreSize": {
                  "X": 0.1703,
                  "Y": 0.1069
                },
                "LeftMargin": 531.0,
                "RightMargin": 531.0,
                "TopMargin": 570.2458,
                "BottomMargin": 72.7542,
                "Tag": 896,
                "ActionTag": -1473572840,
                "Size": {
                  "X": 218.0,
                  "Y": 77.0
                },
                "Name": "btn_yes",
                "ctype": "ButtonObjectData"
              },
              {
                "IsCustomSize": true,
                "FontSize": 26,
                "LabelText": "姓       名:",
                "FontResource": {
                  "Type": "Normal",
                  "Path": "fonts/lanting.TTF",
                  "Plist": ""
                },
                "HorizontalAlignmentType": "HT_Right",
                "OutlineColor": {
                  "G": 0,
                  "B": 0
                },
                "ShadowColor": {
                  "R": 110,
                  "G": 110,
                  "B": 110
                },
                "ShadowOffsetX": 2.0,
                "ShadowOffsetY": -2.0,
                "AnchorPoint": {
                  "ScaleX": 1.0,
                  "ScaleY": 0.5
                },
                "Position": {
                  "X": 456.5537,
                  "Y": 534.8107
                },
                "Scale": {
                  "ScaleX": 1.0,
                  "ScaleY": 1.0
                },
                "CColor": {
                  "R": 115,
                  "G": 136,
                  "B": 117
                },
                "IconVisible": false,
                "PrePosition": {
                  "X": 0.3567,
                  "Y": 0.7428
                },
                "PreSize": {
                  "X": 0.0859,
                  "Y": 0.0417
                },
                "LeftMargin": 346.5537,
                "RightMargin": 823.4463,
                "TopMargin": 170.1893,
                "BottomMargin": 519.8107,
                "Tag": 897,
                "ActionTag": -478545051,
                "Size": {
                  "X": 110.0,
                  "Y": 30.0
                },
                "Name": "Text_ren",
                "ctype": "TextObjectData"
              },
              {
                "IsCustomSize": true,
                "FontSize": 26,
                "LabelText": "电话号码:",
                "FontResource": {
                  "Type": "Normal",
                  "Path": "fonts/lanting.TTF",
                  "Plist": ""
                },
                "HorizontalAlignmentType": "HT_Right",
                "OutlineColor": {
                  "G": 0,
                  "B": 0
                },
                "ShadowColor": {
                  "R": 110,
                  "G": 110,
                  "B": 110
                },
                "ShadowOffsetX": 2.0,
                "ShadowOffsetY": -2.0,
                "AnchorPoint": {
                  "ScaleX": 1.0,
                  "ScaleY": 0.5
                },
                "Position": {
                  "X": 456.5533,
                  "Y": 469.1106
                },
                "Scale": {
                  "ScaleX": 1.0,
                  "ScaleY": 1.0
                },
                "CColor": {
                  "R": 115,
                  "G": 136,
                  "B": 117
                },
                "IconVisible": false,
                "PrePosition": {
                  "X": 0.3567,
                  "Y": 0.6515
                },
                "PreSize": {
                  "X": 0.0938,
                  "Y": 0.0403
                },
                "LeftMargin": 336.5533,
                "RightMargin": 823.4467,
                "TopMargin": 236.3894,
                "BottomMargin": 454.6106,
                "Tag": 898,
                "ActionTag": 971539112,
                "Size": {
                  "X": 120.0,
                  "Y": 29.0
                },
                "Name": "Text_desc_0",
                "ctype": "TextObjectData"
              },
              {
                "IsCustomSize": true,
                "FontSize": 26,
                "LabelText": "所在地区:",
                "FontResource": {
                  "Type": "Normal",
                  "Path": "fonts/lanting.TTF",
                  "Plist": ""
                },
                "HorizontalAlignmentType": "HT_Right",
                "OutlineColor": {
                  "G": 0,
                  "B": 0
                },
                "ShadowColor": {
                  "R": 110,
                  "G": 110,
                  "B": 110
                },
                "ShadowOffsetX": 2.0,
                "ShadowOffsetY": -2.0,
                "AnchorPoint": {
                  "ScaleX": 1.0,
                  "ScaleY": 0.5
                },
                "Position": {
                  "X": 456.5529,
                  "Y": 403.912
                },
                "Scale": {
                  "ScaleX": 1.0,
                  "ScaleY": 1.0
                },
                "CColor": {
                  "R": 115,
                  "G": 136,
                  "B": 117
                },
                "IconVisible": false,
                "PrePosition": {
                  "X": 0.3567,
                  "Y": 0.561
                },
                "PreSize": {
                  "X": 0.0938,
                  "Y": 0.0403
                },
                "LeftMargin": 336.5529,
                "RightMargin": 823.4471,
                "TopMargin": 301.588,
                "BottomMargin": 389.412,
                "Tag": 899,
                "ActionTag": -2040368522,
                "Size": {
                  "X": 120.0,
                  "Y": 29.0
                },
                "Name": "Text_desc_1",
                "ctype": "TextObjectData"
              },
              {
                "IsCustomSize": true,
                "FontSize": 26,
                "LabelText": "详细地址:",
                "FontResource": {
                  "Type": "Normal",
                  "Path": "fonts/lanting.TTF",
                  "Plist": ""
                },
                "HorizontalAlignmentType": "HT_Right",
                "OutlineColor": {
                  "G": 0,
                  "B": 0
                },
                "ShadowColor": {
                  "R": 110,
                  "G": 110,
                  "B": 110
                },
                "ShadowOffsetX": 2.0,
                "ShadowOffsetY": -2.0,
                "AnchorPoint": {
                  "ScaleX": 1.0,
                  "ScaleY": 0.5
                },
                "Position": {
                  "X": 456.5534,
                  "Y": 347.7717
                },
                "Scale": {
                  "ScaleX": 1.0,
                  "ScaleY": 1.0
                },
                "CColor": {
                  "R": 115,
                  "G": 136,
                  "B": 117
                },
                "IconVisible": false,
                "PrePosition": {
                  "X": 0.3567,
                  "Y": 0.483
                },
                "PreSize": {
                  "X": 0.0938,
                  "Y": 0.0403
                },
                "LeftMargin": 336.5534,
                "RightMargin": 823.4466,
                "TopMargin": 357.7283,
                "BottomMargin": 333.2717,
                "Tag": 900,
                "ActionTag": -1942126164,
                "Size": {
                  "X": 120.0,
                  "Y": 29.0
                },
                "Name": "Text_desc_2",
                "ctype": "TextObjectData"
              },
              {
                "FontSize": 14,
                "ButtonText": "",
                "TextColor": {
                  "R": 65,
                  "G": 65,
                  "B": 70
                },
                "NormalFileData": {
                  "Type": "Normal",
                  "Path": "common_3.0/btn_guanbi_2.png",
                  "Plist": ""
                },
                "Scale9Enable": true,
                "Scale9OriginX": 15,
                "Scale9OriginY": 11,
                "Scale9Width": 34,
                "Scale9Height": 42,
                "OutlineColor": {
                  "G": 0,
                  "B": 0
                },
                "ShadowColor": {
                  "R": 110,
                  "G": 110,
                  "B": 110
                },
                "ShadowOffsetX": 2.0,
                "ShadowOffsetY": -2.0,
                "TouchEnable": true,
                "AnchorPoint": {
                  "ScaleX": 0.5,
                  "ScaleY": 0.5
                },
                "Position": {
                  "X": 979.69,
                  "Y": 641.74
                },
                "Scale": {
                  "ScaleX": 1.0,
                  "ScaleY": 1.0
                },
                "CColor": {},
                "IconVisible": false,
                "PrePosition": {
                  "X": 0.7654,
                  "Y": 0.8913
                },
                "PreSize": {
                  "X": 0.05,
                  "Y": 0.0889
                },
                "LeftMargin": 947.69,
                "RightMargin": 268.31,
                "TopMargin": 46.26,
                "BottomMargin": 609.74,
                "Tag": 901,
                "ActionTag": 533089725,
                "Size": {
                  "X": 64.0,
                  "Y": 64.0
                },
                "Name": "close",
                "ctype": "ButtonObjectData"
              },
              {
                "FileData": {
                  "Type": "Normal",
                  "Path": "common_3.0/bg_shurukuang.png",
                  "Plist": ""
                },
                "Scale9Enable": true,
                "Scale9OriginX": 11,
                "Scale9OriginY": 13,
                "Scale9Width": 12,
                "Scale9Height": 16,
                "AnchorPoint": {
                  "ScaleX": 0.5,
                  "ScaleY": 0.5
                },
                "Position": {
                  "X": 708.2021,
                  "Y": 276.3399
                },
                "Scale": {
                  "ScaleX": 1.0,
                  "ScaleY": 1.0
                },
                "CColor": {},
                "IconVisible": false,
                "PrePosition": {
                  "X": 0.5533,
                  "Y": 0.3838
                },
                "PreSize": {
                  "X": 0.3695,
                  "Y": 0.2458
                },
                "LeftMargin": 471.7021,
                "RightMargin": 335.2979,
                "TopMargin": 355.1601,
                "BottomMargin": 187.8399,
                "Tag": 902,
                "ActionTag": -1546772322,
                "Size": {
                  "X": 473.0,
                  "Y": 177.0
                },
                "Name": "input_dizhi",
                "ctype": "ImageViewObjectData"
              },
              {
                "FileData": {
                  "Type": "Normal",
                  "Path": "common_3.0/bg_shurukuang.png",
                  "Plist": ""
                },
                "Scale9Enable": true,
                "Scale9OriginX": 11,
                "Scale9OriginY": 13,
                "Scale9Width": 12,
                "Scale9Height": 16,
                "AnchorPoint": {
                  "ScaleX": 0.5,
                  "ScaleY": 0.5
                },
                "Position": {
                  "X": 708.202,
                  "Y": 401.9551
                },
                "Scale": {
                  "ScaleX": 1.0,
                  "ScaleY": 1.0
                },
                "CColor": {},
                "IconVisible": false,
                "PrePosition": {
                  "X": 0.5533,
                  "Y": 0.5583
                },
                "PreSize": {
                  "X": 0.3695,
                  "Y": 0.0833
                },
                "LeftMargin": 471.702,
                "RightMargin": 335.298,
                "TopMargin": 288.0449,
                "BottomMargin": 371.9551,
                "Tag": 903,
                "Children": [
                  {
                    "FileData": {
                      "Type": "Normal",
                      "Path": "ShopOfJiFen_3.0/btn_xuanze.png",
                      "Plist": ""
                    },
                    "Scale9OriginX": 4,
                    "Scale9OriginY": 7,
                    "Scale9Width": 139,
                    "Scale9Height": 57,
                    "AnchorPoint": {
                      "ScaleX": 0.1515,
                      "ScaleY": 0.5745
                    },
                    "Position": {
                      "X": 351.506,
                      "Y": 35.12
                    },
                    "Scale": {
                      "ScaleX": 1.0,
                      "ScaleY": 1.0
                    },
                    "CColor": {},
                    "IconVisible": false,
                    "PrePosition": {
                      "X": 0.7431,
                      "Y": 0.5853
                    },
                    "PreSize": {
                      "X": 0.3108,
                      "Y": 1.1833
                    },
                    "LeftMargin": 329.2355,
                    "RightMargin": -3.2355,
                    "TopMargin": -5.3305,
                    "BottomMargin": -5.6695,
                    "Tag": 904,
                    "ActionTag": 829230531,
                    "Size": {
                      "X": 147.0,
                      "Y": 71.0
                    },
                    "Name": "img_arrow",
                    "ctype": "ImageViewObjectData"
                  }
                ],
                "ActionTag": 1874891770,
                "Size": {
                  "X": 473.0,
                  "Y": 60.0
                },
                "Name": "input_dizhi_2",
                "ctype": "ImageViewObjectData"
              },
              {
                "FileData": {
                  "Type": "Normal",
                  "Path": "common_3.0/bg_shurukuang.png",
                  "Plist": ""
                },
                "Scale9Enable": true,
                "Scale9OriginX": 11,
                "Scale9OriginY": 13,
                "Scale9Width": 12,
                "Scale9Height": 16,
                "AnchorPoint": {
                  "ScaleX": 0.5,
                  "ScaleY": 0.5
                },
                "Position": {
                  "X": 708.2014,
                  "Y": 467.3932
                },
                "Scale": {
                  "ScaleX": 1.0,
                  "ScaleY": 1.0
                },
                "CColor": {},
                "IconVisible": false,
                "PrePosition": {
                  "X": 0.5533,
                  "Y": 0.6492
                },
                "PreSize": {
                  "X": 0.3695,
                  "Y": 0.0833
                },
                "LeftMargin": 471.7014,
                "RightMargin": 335.2986,
                "TopMargin": 222.6068,
                "BottomMargin": 437.3932,
                "Tag": 905,
                "ActionTag": 256648127,
                "Size": {
                  "X": 473.0,
                  "Y": 60.0
                },
                "Name": "input_number",
                "ctype": "ImageViewObjectData"
              },
              {
                "FileData": {
                  "Type": "Normal",
                  "Path": "common_3.0/bg_shurukuang.png",
                  "Plist": ""
                },
                "Scale9Enable": true,
                "Scale9OriginX": 11,
                "Scale9OriginY": 13,
                "Scale9Width": 12,
                "Scale9Height": 16,
                "AnchorPoint": {
                  "ScaleX": 0.5,
                  "ScaleY": 0.5
                },
                "Position": {
                  "X": 708.2006,
                  "Y": 534.8105
                },
                "Scale": {
                  "ScaleX": 1.0,
                  "ScaleY": 1.0
                },
                "CColor": {},
                "IconVisible": false,
                "PrePosition": {
                  "X": 0.5533,
                  "Y": 0.7428
                },
                "PreSize": {
                  "X": 0.3695,
                  "Y": 0.0833
                },
                "LeftMargin": 471.7006,
                "RightMargin": 335.2994,
                "TopMargin": 155.1895,
                "BottomMargin": 504.8105,
                "Tag": 906,
                "ActionTag": 1837368590,
                "Size": {
                  "X": 473.0,
                  "Y": 60.0
                },
                "Name": "input_ren",
                "ctype": "ImageViewObjectData"
              },
              {
                "ClipAble": false,
                "BackColorAlpha": 76,
                "ComboBoxIndex": 1,
                "SingleColor": {
                  "R": 0,
                  "G": 0,
                  "B": 0
                },
                "FirstColor": {
                  "R": 150,
                  "G": 200
                },
                "EndColor": {},
                "ColorVector": {
                  "ScaleY": 1.0
                },
                "Scale9Width": 1,
                "Scale9Height": 1,
                "TouchEnable": true,
                "AnchorPoint": {
                  "ScaleX": 0.5,
                  "ScaleY": 0.5
                },
                "Position": {
                  "X": 640.0,
                  "Y": 360.0
                },
                "Scale": {
                  "ScaleX": 1.0,
                  "ScaleY": 1.0
                },
                "CColor": {},
                "IconVisible": false,
                "PositionPercentXEnabled": true,
                "PositionPercentYEnabled": true,
                "PrePosition": {
                  "X": 0.5,
                  "Y": 0.5
                },
                "PreSize": {
                  "X": 1.0,
                  "Y": 1.0
                },
                "Tag": 907,
                "Children": [
                  {
                    "FileData": {
                      "Type": "Normal",
                      "Path": "common_3.0/bg_xiaokuang.png",
                      "Plist": ""
                    },
                    "Scale9Enable": true,
                    "Scale9OriginX": 338,
                    "Scale9OriginY": 63,
                    "Scale9Width": 76,
                    "Scale9Height": 13,
                    "TouchEnable": true,
                    "AnchorPoint": {
                      "ScaleX": 0.5,
                      "ScaleY": 0.5
                    },
                    "Position": {
                      "X": 640.0,
                      "Y": 360.0
                    },
                    "Scale": {
                      "ScaleX": 1.0,
                      "ScaleY": 1.0
                    },
                    "CColor": {},
                    "IconVisible": false,
                    "PositionPercentXEnabled": true,
                    "PositionPercentYEnabled": true,
                    "PrePosition": {
                      "X": 0.5,
                      "Y": 0.5
                    },
                    "PreSize": {
                      "X": 0.5391,
                      "Y": 0.8611
                    },
                    "LeftMargin": 295.0,
                    "RightMargin": 295.0,
                    "TopMargin": 50.0,
                    "BottomMargin": 50.0,
                    "Tag": 908,
                    "ActionTag": 1011624884,
                    "Size": {
                      "X": 690.0,
                      "Y": 620.0
                    },
                    "Name": "bg_1",
                    "ctype": "ImageViewObjectData"
                  },
                  {
                    "FileData": {
                      "Type": "Normal",
                      "Path": "ShopOfJiFen_3.0/title_suozaidiqu.png",
                      "Plist": ""
                    },
                    "Scale9OriginX": 43,
                    "Scale9OriginY": 10,
                    "Scale9Width": 52,
                    "Scale9Height": 17,
                    "AnchorPoint": {
                      "ScaleX": 0.5,
                      "ScaleY": 0.5
                    },
                    "Position": {
                      "X": 640.0,
                      "Y": 642.5334
                    },
                    "Scale": {
                      "ScaleX": 1.0,
                      "ScaleY": 1.0
                    },
                    "CColor": {},
                    "IconVisible": false,
                    "PositionPercentXEnabled": true,
                    "PrePosition": {
                      "X": 0.5,
                      "Y": 0.8924
                    },
                    "PreSize": {
                      "X": 0.1078,
                      "Y": 0.0514
                    },
                    "LeftMargin": 571.0,
                    "RightMargin": 571.0,
                    "TopMargin": 58.9666,
                    "BottomMargin": 624.0334,
                    "Tag": 909,
                    "ActionTag": 1121326359,
                    "Size": {
                      "X": 138.0,
                      "Y": 37.0
                    },
                    "Name": "Image_7",
                    "ctype": "ImageViewObjectData"
                  },
                  {
                    "DirectionType": "Vertical",
                    "HorizontalType": "Align_HorizontalCenter",
                    "IsBounceEnabled": true,
                    "ScrollDirectionType": 0,
                    "ClipAble": true,
                    "BackColorAlpha": 3,
                    "ComboBoxIndex": 1,
                    "SingleColor": {
                      "R": 144,
                      "G": 238,
                      "B": 144
                    },
                    "FirstColor": {
                      "R": 150,
                      "G": 150
                    },
                    "EndColor": {},
                    "ColorVector": {
                      "ScaleY": 1.0
                    },
                    "Scale9Width": 1,
                    "Scale9Height": 1,
                    "TouchEnable": true,
                    "AnchorPoint": {},
                    "Position": {
                      "X": 321.1663,
                      "Y": 107.648
                    },
                    "Scale": {
                      "ScaleX": 1.0,
                      "ScaleY": 1.0
                    },
                    "CColor": {},
                    "IconVisible": false,
                    "PrePosition": {
                      "X": 0.2509,
                      "Y": 0.1495
                    },
                    "PreSize": {
                      "X": 0.1563,
                      "Y": 0.625
                    },
                    "LeftMargin": 321.1663,
                    "RightMargin": 758.8337,
                    "TopMargin": 162.352,
                    "BottomMargin": 107.648,
                    "Tag": 910,
                    "ActionTag": -177153533,
                    "Size": {
                      "X": 200.0,
                      "Y": 450.0
                    },
                    "Name": "info_list",
                    "ctype": "ListViewObjectData"
                  },
                  {
                    "DirectionType": "Vertical",
                    "HorizontalType": "Align_HorizontalCenter",
                    "IsBounceEnabled": true,
                    "ScrollDirectionType": 0,
                    "ClipAble": true,
                    "BackColorAlpha": 3,
                    "ComboBoxIndex": 1,
                    "SingleColor": {
                      "R": 144,
                      "G": 238,
                      "B": 144
                    },
                    "FirstColor": {
                      "R": 150,
                      "G": 150
                    },
                    "EndColor": {},
                    "ColorVector": {
                      "ScaleY": 1.0
                    },
                    "Scale9Width": 1,
                    "Scale9Height": 1,
                    "TouchEnable": true,
                    "AnchorPoint": {
                      "ScaleX": 0.5
                    },
                    "Position": {
                      "X": 640.0,
                      "Y": 107.648
                    },
                    "Scale": {
                      "ScaleX": 1.0,
                      "ScaleY": 1.0
                    },
                    "CColor": {},
                    "IconVisible": false,
                    "PositionPercentXEnabled": true,
                    "PrePosition": {
                      "X": 0.5,
                      "Y": 0.1495
                    },
                    "PreSize": {
                      "X": 0.1563,
                      "Y": 0.625
                    },
                    "LeftMargin": 540.0,
                    "RightMargin": 540.0,
                    "TopMargin": 162.352,
                    "BottomMargin": 107.648,
                    "Tag": 911,
                    "ActionTag": 12841092,
                    "Size": {
                      "X": 200.0,
                      "Y": 450.0
                    },
                    "Name": "info_list_2",
                    "ctype": "ListViewObjectData"
                  },
                  {
                    "DirectionType": "Vertical",
                    "HorizontalType": "Align_HorizontalCenter",
                    "IsBounceEnabled": true,
                    "ScrollDirectionType": 0,
                    "ClipAble": true,
                    "BackColorAlpha": 3,
                    "ComboBoxIndex": 1,
                    "SingleColor": {
                      "R": 144,
                      "G": 238,
                      "B": 144
                    },
                    "FirstColor": {
                      "R": 150,
                      "G": 150
                    },
                    "EndColor": {},
                    "ColorVector": {
                      "ScaleY": 1.0
                    },
                    "Scale9Width": 1,
                    "Scale9Height": 1,
                    "TouchEnable": true,
                    "AnchorPoint": {},
                    "Position": {
                      "X": 763.0454,
                      "Y": 107.648
                    },
                    "Scale": {
                      "ScaleX": 1.0,
                      "ScaleY": 1.0
                    },
                    "CColor": {},
                    "IconVisible": false,
                    "PrePosition": {
                      "X": 0.5961,
                      "Y": 0.1495
                    },
                    "PreSize": {
                      "X": 0.1563,
                      "Y": 0.625
                    },
                    "LeftMargin": 763.0454,
                    "RightMargin": 316.9546,
                    "TopMargin": 162.352,
                    "BottomMargin": 107.648,
                    "Tag": 912,
                    "ActionTag": -1800809200,
                    "Size": {
                      "X": 200.0,
                      "Y": 450.0
                    },
                    "Name": "info_list_3",
                    "ctype": "ListViewObjectData"
                  },
                  {
                    "ClipAble": false,
                    "BackColorAlpha": 0,
                    "ComboBoxIndex": 1,
                    "SingleColor": {
                      "R": 150,
                      "G": 200
                    },
                    "FirstColor": {
                      "R": 150,
                      "G": 200
                    },
                    "EndColor": {},
                    "ColorVector": {
                      "ScaleY": 1.0
                    },
                    "Scale9Width": 1,
                    "Scale9Height": 1,
                    "TouchEnable": true,
                    "AnchorPoint": {},
                    "Position": {
                      "X": 1543.1611,
                      "Y": 433.2882
                    },
                    "Scale": {
                      "ScaleX": 1.0,
                      "ScaleY": 1.0
                    },
                    "CColor": {},
                    "IconVisible": false,
                    "PrePosition": {
                      "X": 1.2056,
                      "Y": 0.6018
                    },
                    "PreSize": {
                      "X": 0.1937,
                      "Y": 0.0694
                    },
                    "LeftMargin": 1543.1611,
                    "RightMargin": -511.1611,
                    "TopMargin": 236.7118,
                    "BottomMargin": 433.2882,
                    "Tag": 913,
                    "Children": [
                      {
                        "FileData": {
                          "Type": "Normal",
                          "Path": "ShopOfJiFen_3.0/bg_xuanzhong.png",
                          "Plist": ""
                        },
                        "Scale9Enable": true,
                        "Scale9OriginX": 33,
                        "Scale9OriginY": 7,
                        "Scale9Width": 156,
                        "Scale9Height": 34,
                        "AnchorPoint": {
                          "ScaleX": 0.5,
                          "ScaleY": 0.5
                        },
                        "Position": {
                          "X": 124.0,
                          "Y": 25.0
                        },
                        "Scale": {
                          "ScaleX": 1.0,
                          "ScaleY": 1.0
                        },
                        "CColor": {},
                        "IconVisible": false,
                        "PositionPercentXEnabled": true,
                        "PositionPercentYEnabled": true,
                        "PrePosition": {
                          "X": 0.5,
                          "Y": 0.5
                        },
                        "PreSize": {
                          "X": 0.8952,
                          "Y": 0.96
                        },
                        "LeftMargin": 13.0,
                        "RightMargin": 13.0,
                        "TopMargin": 1.0,
                        "BottomMargin": 1.0,
                        "Tag": 914,
                        "ActionTag": 1120761298,
                        "Size": {
                          "X": 222.0,
                          "Y": 48.0
                        },
                        "Name": "Image_bg",
                        "ctype": "ImageViewObjectData"
                      },
                      {
                        "IsCustomSize": true,
                        "FontSize": 22,
                        "LabelText": "新疆维吾尔族自治区",
                        "FontResource": {
                          "Type": "Normal",
                          "Path": "fonts/lanting.TTF",
                          "Plist": ""
                        },
                        "HorizontalAlignmentType": "HT_Center",
                        "OutlineColor": {
                          "G": 0,
                          "B": 0
                        },
                        "ShadowColor": {
                          "R": 110,
                          "G": 110,
                          "B": 110
                        },
                        "ShadowOffsetX": 2.0,
                        "ShadowOffsetY": -2.0,
                        "AnchorPoint": {
                          "ScaleX": 0.5,
                          "ScaleY": 0.5
                        },
                        "Position": {
                          "X": 124.0,
                          "Y": 25.0
                        },
                        "Scale": {
                          "ScaleX": 1.0,
                          "ScaleY": 1.0
                        },
                        "CColor": {
                          "R": 115,
                          "G": 136,
                          "B": 117
                        },
                        "IconVisible": false,
                        "PositionPercentXEnabled": true,
                        "PositionPercentYEnabled": true,
                        "PrePosition": {
                          "X": 0.5,
                          "Y": 0.5
                        },
                        "PreSize": {
                          "X": 0.9516,
                          "Y": 0.62
                        },
                        "LeftMargin": 6.0,
                        "RightMargin": 6.0,
                        "TopMargin": 9.5,
                        "BottomMargin": 9.5,
                        "Tag": 915,
                        "ActionTag": 304817783,
                        "Size": {
                          "X": 236.0,
                          "Y": 31.0
                        },
                        "Name": "Text_1",
                        "ctype": "TextObjectData"
                      }
                    ],
                    "ActionTag": 198311298,
                    "Size": {
                      "X": 248.0,
                      "Y": 50.0
                    },
                    "Name": "info_cell",
                    "ctype": "PanelObjectData"
                  },
                  {
                    "FontSize": 26,
                    "LabelText": "选择地址",
                    "FontResource": {
                      "Type": "Default",
                      "Path": "",
                      "Plist": ""
                    },
                    "OutlineColor": {
                      "G": 0,
                      "B": 0
                    },
                    "ShadowColor": {
                      "R": 110,
                      "G": 110,
                      "B": 110
                    },
                    "ShadowOffsetX": 2.0,
                    "ShadowOffsetY": -2.0,
                    "AnchorPoint": {
                      "ScaleX": 0.5,
                      "ScaleY": 0.5
                    },
                    "Position": {
                      "X": 643.9938,
                      "Y": 620.5457
                    },
                    "Scale": {
                      "ScaleX": 1.0,
                      "ScaleY": 1.0
                    },
                    "CColor": {
                      "R": 0,
                      "G": 0,
                      "B": 0
                    },
                    "IconVisible": false,
                    "PrePosition": {
                      "X": 0.5031,
                      "Y": 0.8619
                    },
                    "PreSize": {
                      "X": 0.0812,
                      "Y": 0.0361
                    },
                    "LeftMargin": 591.9938,
                    "RightMargin": 584.0062,
                    "TopMargin": 86.4543,
                    "BottomMargin": 607.5457,
                    "Tag": 916,
                    "ActionTag": 866243791,
                    "Size": {
                      "X": 104.0,
                      "Y": 26.0
                    },
                    "VisibleForFrame": false,
                    "Name": "txt_title",
                    "ctype": "TextObjectData"
                  },
                  {
                    "FontSize": 14,
                    "ButtonText": "",
                    "TextColor": {
                      "R": 65,
                      "G": 65,
                      "B": 70
                    },
                    "NormalFileData": {
                      "Type": "Normal",
                      "Path": "ShopOfJiFen/btnCity_yes.png",
                      "Plist": ""
                    },
                    "Scale9Enable": true,
                    "Scale9OriginX": 15,
                    "Scale9OriginY": 11,
                    "Scale9Width": 181,
                    "Scale9Height": 67,
                    "OutlineColor": {
                      "G": 0,
                      "B": 0
                    },
                    "ShadowColor": {
                      "R": 110,
                      "G": 110,
                      "B": 110
                    },
                    "ShadowOffsetX": 2.0,
                    "ShadowOffsetY": -2.0,
                    "TouchEnable": true,
                    "AnchorPoint": {
                      "ScaleX": 0.5,
                      "ScaleY": 0.5
                    },
                    "Position": {
                      "X": 1742.4742,
                      "Y": 160.4837
                    },
                    "Scale": {
                      "ScaleX": 1.0,
                      "ScaleY": 1.0
                    },
                    "CColor": {},
                    "IconVisible": false,
                    "PrePosition": {
                      "X": 1.3613,
                      "Y": 0.2229
                    },
                    "PreSize": {
                      "X": 0.1648,
                      "Y": 0.1236
                    },
                    "LeftMargin": 1636.9742,
                    "RightMargin": -567.9742,
                    "TopMargin": 515.0163,
                    "BottomMargin": 115.9837,
                    "Tag": 917,
                    "ActionTag": 3206322,
                    "Size": {
                      "X": 211.0,
                      "Y": 89.0
                    },
                    "Name": "btn_yes2",
                    "ctype": "ButtonObjectData"
                  },
                  {
                    "FontSize": 14,
                    "ButtonText": "",
                    "TextColor": {
                      "R": 65,
                      "G": 65,
                      "B": 70
                    },
                    "NormalFileData": {
                      "Type": "Normal",
                      "Path": "common_3.0/btn_guanbi_2.png",
                      "Plist": ""
                    },
                    "Scale9Enable": true,
                    "Scale9OriginX": 15,
                    "Scale9OriginY": 11,
                    "Scale9Width": 34,
                    "Scale9Height": 42,
                    "OutlineColor": {
                      "G": 0,
                      "B": 0
                    },
                    "ShadowColor": {
                      "R": 110,
                      "G": 110,
                      "B": 110
                    },
                    "ShadowOffsetX": 2.0,
                    "ShadowOffsetY": -2.0,
                    "TouchEnable": true,
                    "AnchorPoint": {
                      "ScaleX": 0.5,
                      "ScaleY": 0.5
                    },
                    "Position": {
                      "X": 979.69,
                      "Y": 641.74
                    },
                    "Scale": {
                      "ScaleX": 1.0,
                      "ScaleY": 1.0
                    },
                    "CColor": {},
                    "IconVisible": false,
                    "PrePosition": {
                      "X": 0.7654,
                      "Y": 0.8913
                    },
                    "PreSize": {
                      "X": 0.05,
                      "Y": 0.0889
                    },
                    "LeftMargin": 947.69,
                    "RightMargin": 268.31,
                    "TopMargin": 46.26,
                    "BottomMargin": 609.74,
                    "Tag": 918,
                    "ActionTag": -1298019998,
                    "Size": {
                      "X": 64.0,
                      "Y": 64.0
                    },
                    "Name": "btn_close",
                    "ctype": "ButtonObjectData"
                  },
                  {
                    "FontSize": 20,
                    "ButtonText": "请选择省份",
                    "FontResource": {
                      "Type": "Normal",
                      "Path": "fonts/lanting.TTF",
                      "Plist": ""
                    },
                    "TextColor": {
                      "R": 182,
                      "G": 182,
                      "B": 181
                    },
                    "PressedFileData": {
                      "Type": "Normal",
                      "Path": "ShopOfJiFen/btnCity_s.png",
                      "Plist": ""
                    },
                    "NormalFileData": {
                      "Type": "Normal",
                      "Path": "ShopOfJiFen/btnCity_n.png",
                      "Plist": ""
                    },
                    "Scale9Enable": true,
                    "Scale9OriginX": 15,
                    "Scale9OriginY": 11,
                    "Scale9Width": 114,
                    "Scale9Height": 13,
                    "OutlineColor": {
                      "G": 0,
                      "B": 0
                    },
                    "ShadowColor": {
                      "R": 110,
                      "G": 110,
                      "B": 110
                    },
                    "ShadowOffsetX": 2.0,
                    "ShadowOffsetY": -2.0,
                    "TouchEnable": true,
                    "AnchorPoint": {
                      "ScaleX": 0.5,
                      "ScaleY": 0.5
                    },
                    "Position": {
                      "X": 418.6901,
                      "Y": 576.6741
                    },
                    "Scale": {
                      "ScaleX": 1.0,
                      "ScaleY": 1.0
                    },
                    "CColor": {},
                    "IconVisible": false,
                    "PrePosition": {
                      "X": 0.3271,
                      "Y": 0.8009
                    },
                    "PreSize": {
                      "X": 0.1125,
                      "Y": 0.0486
                    },
                    "LeftMargin": 346.6901,
                    "RightMargin": 789.3099,
                    "TopMargin": 125.8259,
                    "BottomMargin": 559.1741,
                    "Tag": 919,
                    "ActionTag": -255875422,
                    "Size": {
                      "X": 144.0,
                      "Y": 35.0
                    },
                    "Name": "btn_1",
                    "ctype": "ButtonObjectData"
                  },
                  {
                    "FontSize": 20,
                    "ButtonText": "请选择城市",
                    "FontResource": {
                      "Type": "Normal",
                      "Path": "fonts/lanting.TTF",
                      "Plist": ""
                    },
                    "TextColor": {
                      "R": 182,
                      "G": 182,
                      "B": 181
                    },
                    "PressedFileData": {
                      "Type": "Normal",
                      "Path": "ShopOfJiFen/btnCity_s.png",
                      "Plist": ""
                    },
                    "NormalFileData": {
                      "Type": "Normal",
                      "Path": "ShopOfJiFen/btnCity_n.png",
                      "Plist": ""
                    },
                    "Scale9Enable": true,
                    "Scale9OriginX": 15,
                    "Scale9OriginY": 11,
                    "Scale9Width": 114,
                    "Scale9Height": 13,
                    "OutlineColor": {
                      "G": 0,
                      "B": 0
                    },
                    "ShadowColor": {
                      "R": 110,
                      "G": 110,
                      "B": 110
                    },
                    "ShadowOffsetX": 2.0,
                    "ShadowOffsetY": -2.0,
                    "TouchEnable": true,
                    "AnchorPoint": {
                      "ScaleX": 0.5,
                      "ScaleY": 0.5
                    },
                    "Position": {
                      "X": 640.0,
                      "Y": 576.6741
                    },
                    "Scale": {
                      "ScaleX": 1.0,
                      "ScaleY": 1.0
                    },
                    "CColor": {},
                    "IconVisible": false,
                    "PositionPercentXEnabled": true,
                    "PrePosition": {
                      "X": 0.5,
                      "Y": 0.8009
                    },
                    "PreSize": {
                      "X": 0.1125,
                      "Y": 0.0486
                    },
                    "LeftMargin": 568.0,
                    "RightMargin": 568.0,
                    "TopMargin": 125.8259,
                    "BottomMargin": 559.1741,
                    "Tag": 920,
                    "ActionTag": -1804311301,
                    "Size": {
                      "X": 144.0,
                      "Y": 35.0
                    },
                    "Name": "btn_2",
                    "ctype": "ButtonObjectData"
                  },
                  {
                    "FontSize": 20,
                    "ButtonText": "请选择县/区",
                    "FontResource": {
                      "Type": "Normal",
                      "Path": "fonts/lanting.TTF",
                      "Plist": ""
                    },
                    "TextColor": {
                      "R": 182,
                      "G": 182,
                      "B": 181
                    },
                    "PressedFileData": {
                      "Type": "Normal",
                      "Path": "ShopOfJiFen/btnCity_s.png",
                      "Plist": ""
                    },
                    "NormalFileData": {
                      "Type": "Normal",
                      "Path": "ShopOfJiFen/btnCity_n.png",
                      "Plist": ""
                    },
                    "Scale9Enable": true,
                    "Scale9OriginX": 15,
                    "Scale9OriginY": 11,
                    "Scale9Width": 114,
                    "Scale9Height": 13,
                    "OutlineColor": {
                      "G": 0,
                      "B": 0
                    },
                    "ShadowColor": {
                      "R": 110,
                      "G": 110,
                      "B": 110
                    },
                    "ShadowOffsetX": 2.0,
                    "ShadowOffsetY": -2.0,
                    "TouchEnable": true,
                    "AnchorPoint": {
                      "ScaleX": 0.5,
                      "ScaleY": 0.5
                    },
                    "Position": {
                      "X": 862.0023,
                      "Y": 576.6741
                    },
                    "Scale": {
                      "ScaleX": 1.0,
                      "ScaleY": 1.0
                    },
                    "CColor": {},
                    "IconVisible": false,
                    "PrePosition": {
                      "X": 0.6734,
                      "Y": 0.8009
                    },
                    "PreSize": {
                      "X": 0.1125,
                      "Y": 0.0486
                    },
                    "LeftMargin": 790.0023,
                    "RightMargin": 345.9977,
                    "TopMargin": 125.8259,
                    "BottomMargin": 559.1741,
                    "Tag": 921,
                    "ActionTag": -551780119,
                    "Size": {
                      "X": 144.0,
                      "Y": 35.0
                    },
                    "Name": "btn_3",
                    "ctype": "ButtonObjectData"
                  },
                  {
                    "FileData": {
                      "Type": "Normal",
                      "Path": "common_3.0/fengexian.png",
                      "Plist": ""
                    },
                    "Scale9OriginY": 10,
                    "Scale9Width": 1,
                    "Scale9Height": 11,
                    "AnchorPoint": {
                      "ScaleX": 0.5,
                      "ScaleY": 0.5
                    },
                    "Position": {
                      "X": 530.6533,
                      "Y": 346.032
                    },
                    "Scale": {
                      "ScaleX": 1.0,
                      "ScaleY": 1.0
                    },
                    "CColor": {},
                    "IconVisible": false,
                    "PositionPercentYEnabled": true,
                    "PrePosition": {
                      "X": 0.4146,
                      "Y": 0.4806
                    },
                    "PreSize": {
                      "X": 0.0008,
                      "Y": 0.6944
                    },
                    "LeftMargin": 530.1533,
                    "RightMargin": 748.8467,
                    "TopMargin": 123.968,
                    "BottomMargin": 96.032,
                    "Tag": 922,
                    "ActionTag": -1887446817,
                    "Size": {
                      "X": 1.0,
                      "Y": 500.0
                    },
                    "Name": "Image_fengexian",
                    "ctype": "ImageViewObjectData"
                  },
                  {
                    "FileData": {
                      "Type": "Normal",
                      "Path": "common_3.0/fengexian.png",
                      "Plist": ""
                    },
                    "Scale9OriginY": 10,
                    "Scale9Width": 1,
                    "Scale9Height": 11,
                    "AnchorPoint": {
                      "ScaleX": 0.5,
                      "ScaleY": 0.5
                    },
                    "Position": {
                      "X": 754.5382,
                      "Y": 346.032
                    },
                    "Scale": {
                      "ScaleX": 1.0,
                      "ScaleY": 1.0
                    },
                    "CColor": {},
                    "IconVisible": false,
                    "PositionPercentYEnabled": true,
                    "PrePosition": {
                      "X": 0.5895,
                      "Y": 0.4806
                    },
                    "PreSize": {
                      "X": 0.0008,
                      "Y": 0.6944
                    },
                    "LeftMargin": 754.0382,
                    "RightMargin": 524.9618,
                    "TopMargin": 123.968,
                    "BottomMargin": 96.032,
                    "Tag": 923,
                    "ActionTag": -1809748956,
                    "Size": {
                      "X": 1.0,
                      "Y": 500.0
                    },
                    "Name": "Image_fengexian_0",
                    "ctype": "ImageViewObjectData"
                  }
                ],
                "ActionTag": -274309820,
                "Size": {
                  "X": 1280.0,
                  "Y": 720.0
                },
                "Name": "bg_infolist",
                "ctype": "PanelObjectData"
              },
              {
                "FontSize": 30,
                "LabelText": "确认消耗XXX礼券兑换XXXX",
                "FontResource": {
                  "Type": "Normal",
                  "Path": "fonts/lanting.TTF",
                  "Plist": ""
                },
                "HorizontalAlignmentType": "HT_Center",
                "OutlineColor": {
                  "G": 0,
                  "B": 0
                },
                "ShadowColor": {
                  "R": 110,
                  "G": 110,
                  "B": 110
                },
                "ShadowOffsetX": 2.0,
                "ShadowOffsetY": -2.0,
                "AnchorPoint": {
                  "ScaleX": 0.5,
                  "ScaleY": 0.5
                },
                "Position": {
                  "X": 640.0,
                  "Y": 590.1626
                },
                "Scale": {
                  "ScaleX": 1.0,
                  "ScaleY": 1.0
                },
                "CColor": {
                  "G": 111,
                  "B": 32
                },
                "IconVisible": false,
                "PositionPercentXEnabled": true,
                "PrePosition": {
                  "X": 0.5,
                  "Y": 0.8197
                },
                "PreSize": {
                  "X": 0.3102,
                  "Y": 0.0472
                },
                "LeftMargin": 441.5,
                "RightMargin": 441.5,
                "TopMargin": 112.8374,
                "BottomMargin": 573.1626,
                "Tag": 583,
                "ActionTag": -555951586,
                "Size": {
                  "X": 397.0,
                  "Y": 34.0
                },
                "Name": "Text_yes",
                "ctype": "TextObjectData"
              },
              {
                "FontSize": 18,
                "LabelText": "请务必填写真实姓名和联系方式，以便兑换商品后准确发货。",
                "FontResource": {
                  "Type": "Normal",
                  "Path": "fonts/lanting.TTF",
                  "Plist": ""
                },
                "HorizontalAlignmentType": "HT_Center",
                "OutlineColor": {
                  "G": 0,
                  "B": 0
                },
                "ShadowColor": {
                  "R": 110,
                  "G": 110,
                  "B": 110
                },
                "ShadowOffsetX": 2.0,
                "ShadowOffsetY": -2.0,
                "AnchorPoint": {
                  "ScaleX": 0.5,
                  "ScaleY": 0.5
                },
                "Position": {
                  "X": 640.0,
                  "Y": 165.7257
                },
                "Scale": {
                  "ScaleX": 1.0,
                  "ScaleY": 1.0
                },
                "CColor": {
                  "R": 182,
                  "G": 182,
                  "B": 181
                },
                "IconVisible": false,
                "PositionPercentXEnabled": true,
                "PrePosition": {
                  "X": 0.5,
                  "Y": 0.2302
                },
                "PreSize": {
                  "X": 0.3742,
                  "Y": 0.0292
                },
                "LeftMargin": 400.5,
                "RightMargin": 400.5,
                "TopMargin": 543.7743,
                "BottomMargin": 155.2257,
                "Tag": 434,
                "ActionTag": 1039433187,
                "Size": {
                  "X": 479.0,
                  "Y": 21.0
                },
                "Name": "Text_desc",
                "ctype": "TextObjectData"
              }
            ],
            "ActionTag": 1503659383,
            "Size": {
              "X": 1280.0,
              "Y": 720.0
            },
            "Name": "back",
            "ctype": "PanelObjectData"
          }
        ],
        "Size": {
          "X": 1280.0,
          "Y": 720.0
        },
        "Name": "Layer",
        "ctype": "LayerObjectData"
      },
      "UsedResources": [
        "common_3.0/bg_dikuang.png",
        "common_3.0/bg_shurukuang.png",
        "common_3.0/bg_xiaokuang.png",
        "common_3.0/btn_guanbi_2.png",
        "common_3.0/btn_lv.png",
        "common_3.0/fengexian.png",
        "fonts/lanting.TTF",
        "ShopOfJiFen/btnCity_n.png",
        "ShopOfJiFen/btnCity_s.png",
        "ShopOfJiFen/btnCity_yes.png",
        "ShopOfJiFen_3.0/bg_xuanzhong.png",
        "ShopOfJiFen_3.0/btn_xuanze.png",
        "ShopOfJiFen_3.0/tilte_duihuan.png",
        "ShopOfJiFen_3.0/title_suozaidiqu.png"
      ],
      "ctype": "GameFileData"
    }
  },
  "Type": "Layer"
}